{"v":"4.8.0","meta":{"g":"LottieFiles AE 3.0.2","a":"","k":"","d":"","tc":""},"fr":25,"ip":0,"op":75,"w":550,"h":550,"nm":"global tracking","ddd":0,"assets":[],"layers":[{"ddd":0,"ind":1,"ty":4,"nm":"top line","sr":1,"ks":{"o":{"a":0,"k":100,"ix":11},"r":{"a":0,"k":0,"ix":10},"p":{"a":0,"k":[372,205.38,0],"ix":2},"a":{"a":0,"k":[0,0,0],"ix":1},"s":{"a":0,"k":[100,100,100],"ix":6}},"ao":0,"shapes":[{"ty":"gr","it":[{"ind":0,"ty":"sh","ix":1,"ks":{"a":0,"k":{"i":[[0,0],[0,-112.74],[7.94,-22.18]],"o":[[111.38,5.47],[0,24.92],[0,0]],"v":[[-100,-140.62],[100,69.62],[87.73,140.62]],"c":false},"ix":2},"nm":"Path 1","mn":"ADBE Vector Shape - Group","hd":false},{"ty":"st","c":{"a":0,"k":[0.439215689898,0.713725507259,0.988235294819,1],"ix":3},"o":{"a":0,"k":100,"ix":4},"w":{"a":0,"k":13,"ix":5},"lc":2,"lj":1,"ml":10,"bm":0,"nm":"Stroke 1","mn":"ADBE Vector Graphic - Stroke","hd":false},{"ty":"tr","p":{"a":0,"k":[0,0],"ix":2},"a":{"a":0,"k":[0,0],"ix":1},"s":{"a":0,"k":[100,100],"ix":3},"r":{"a":0,"k":0,"ix":6},"o":{"a":0,"k":100,"ix":7},"sk":{"a":0,"k":0,"ix":4},"sa":{"a":0,"k":0,"ix":5},"nm":"Transform"}],"nm":"Group 1","np":2,"cix":2,"bm":0,"ix":1,"mn":"ADBE Vector Group","hd":false},{"ty":"tm","s":{"a":1,"k":[{"i":{"x":[0.667],"y":[1]},"o":{"x":[0.333],"y":[0]},"t":43,"s":[0]},{"t":53,"s":[100]}],"ix":1},"e":{"a":1,"k":[{"i":{"x":[0.667],"y":[1]},"o":{"x":[0.333],"y":[0]},"t":25,"s":[0]},{"t":34,"s":[100]}],"ix":2},"o":{"a":0,"k":0,"ix":3},"m":1,"ix":2,"nm":"Trim Paths 1","mn":"ADBE Vector Filter - Trim","hd":false}],"ip":0,"op":75,"st":0,"bm":0},{"ddd":0,"ind":2,"ty":4,"nm":"location","sr":1,"ks":{"o":{"a":0,"k":100,"ix":11},"r":{"a":0,"k":0,"ix":10},"p":{"a":0,"k":[181.909,112.091,0],"ix":2},"a":{"a":0,"k":[191.909,112.091,0],"ix":1},"s":{"a":1,"k":[{"i":{"x":[0.667,0.667,0.667],"y":[1,1,1]},"o":{"x":[0.333,0.333,0.333],"y":[0,0,0]},"t":14,"s":[0,0,100]},{"i":{"x":[0.667,0.667,0.667],"y":[1,1,1]},"o":{"x":[0.333,0.333,0.333],"y":[0,0,0]},"t":22.4,"s":[110,110,100]},{"i":{"x":[0.667,0.667,0.667],"y":[1,1,1]},"o":{"x":[0.167,0.167,0.167],"y":[0,0,0]},"t":26,"s":[100,100,100]},{"i":{"x":[0.667,0.667,0.667],"y":[1,1,1]},"o":{"x":[0.333,0.333,0.333],"y":[0,0,0]},"t":34,"s":[100,100,100]},{"i":{"x":[0.667,0.667,0.667],"y":[1,1,1]},"o":{"x":[0.333,0.333,0.333],"y":[0,0,0]},"t":37,"s":[110,110,100]},{"t":45,"s":[0,0,100]}],"ix":6}},"ao":0,"shapes":[{"ty":"gr","it":[{"ind":0,"ty":"sh","ix":1,"ks":{"a":0,"k":{"i":[[-19.28,0],[0,-19.28],[19.28,0],[0,19.28]],"o":[[19.28,0],[0,19.28],[-19.28,0],[0,-19.28]],"v":[[0,-34.909],[34.909,0],[0,34.909],[-34.909,0]],"c":true},"ix":2},"nm":"Path 1","mn":"ADBE Vector Shape - Group","hd":false},{"ty":"fl","c":{"a":0,"k":[0.847058832645,0.29411765933,0.223529413342,1],"ix":4},"o":{"a":0,"k":100,"ix":5},"r":1,"bm":0,"nm":"Fill 1","mn":"ADBE Vector Graphic - Fill","hd":false},{"ty":"tr","p":{"a":0,"k":[191.909,94.636],"ix":2},"a":{"a":0,"k":[0,0],"ix":1},"s":{"a":0,"k":[100,100],"ix":3},"r":{"a":0,"k":0,"ix":6},"o":{"a":0,"k":100,"ix":7},"sk":{"a":0,"k":0,"ix":4},"sa":{"a":0,"k":0,"ix":5},"nm":"Transform"}],"nm":"Group 1","np":2,"cix":2,"bm":0,"ix":1,"mn":"ADBE Vector Group","hd":false},{"ty":"gr","it":[{"ind":0,"ty":"sh","ix":1,"ks":{"a":0,"k":{"i":[[38.542,0.043],[0.043,-38.542],[-2.685,-2.665],[-2.27,2.25],[0,37.341]],"o":[[-38.542,0.043],[0,37.341],[2.27,2.25],[2.685,-2.665],[-0.043,-38.542]],"v":[[0,-87.273],[-69.818,-17.455],[-4.1,85.585],[4.099,85.585],[69.818,-17.455]],"c":true},"ix":2},"nm":"Path 1","mn":"ADBE Vector Shape - Group","hd":false},{"ty":"fl","c":{"a":0,"k":[1,0.474509805441,0.337254911661,1],"ix":4},"o":{"a":0,"k":100,"ix":5},"r":1,"bm":0,"nm":"Fill 1","mn":"ADBE Vector Graphic - Fill","hd":false},{"ty":"tr","p":{"a":0,"k":[191.909,112.091],"ix":2},"a":{"a":0,"k":[0,0],"ix":1},"s":{"a":0,"k":[100,100],"ix":3},"r":{"a":0,"k":0,"ix":6},"o":{"a":0,"k":100,"ix":7},"sk":{"a":0,"k":0,"ix":4},"sa":{"a":0,"k":0,"ix":5},"nm":"Transform"}],"nm":"Group 2","np":2,"cix":2,"bm":0,"ix":2,"mn":"ADBE Vector Group","hd":false}],"ip":0,"op":75,"st":0,"bm":0},{"ddd":0,"ind":3,"ty":4,"nm":"bottom line","sr":1,"ks":{"o":{"a":0,"k":100,"ix":11},"r":{"a":0,"k":0,"ix":10},"p":{"a":0,"k":[177.765,307.955,0],"ix":2},"a":{"a":0,"k":[0,0,0],"ix":1},"s":{"a":0,"k":[100,100,100],"ix":6}},"ao":0,"shapes":[{"ty":"gr","it":[{"ind":0,"ty":"sh","ix":1,"ks":{"a":0,"k":{"i":[[0,0],[0,-54.52],[-116.26,0],[-12.33,2.25]],"o":[[-34,37.39],[0,116.26],[12.99,0],[0,0]],"v":[[-69.535,-176.045],[-124.265,-34.455],[86.235,176.045],[124.265,172.615]],"c":false},"ix":2},"nm":"Path 1","mn":"ADBE Vector Shape - Group","hd":false},{"ty":"st","c":{"a":0,"k":[0.439215689898,0.713725507259,0.988235294819,1],"ix":3},"o":{"a":0,"k":100,"ix":4},"w":{"a":0,"k":13,"ix":5},"lc":2,"lj":1,"ml":10,"bm":0,"nm":"Stroke 1","mn":"ADBE Vector Graphic - Stroke","hd":false},{"ty":"tr","p":{"a":0,"k":[0,0],"ix":2},"a":{"a":0,"k":[0,0],"ix":1},"s":{"a":0,"k":[100,100],"ix":3},"r":{"a":0,"k":0,"ix":6},"o":{"a":0,"k":100,"ix":7},"sk":{"a":0,"k":0,"ix":4},"sa":{"a":0,"k":0,"ix":5},"nm":"Transform"}],"nm":"Group 1","np":2,"cix":2,"bm":0,"ix":1,"mn":"ADBE Vector Group","hd":false},{"ty":"tm","s":{"a":1,"k":[{"i":{"x":[0.667],"y":[1]},"o":{"x":[0.333],"y":[0]},"t":7,"s":[100]},{"t":17,"s":[0]}],"ix":1},"e":{"a":1,"k":[{"i":{"x":[0.667],"y":[1]},"o":{"x":[0.333],"y":[0]},"t":55,"s":[100]},{"t":65,"s":[0]}],"ix":2},"o":{"a":0,"k":0,"ix":3},"m":1,"ix":2,"nm":"Trim Paths 1","mn":"ADBE Vector Filter - Trim","hd":false}],"ip":0,"op":75,"st":0,"bm":0},{"ddd":0,"ind":4,"ty":4,"nm":"box","sr":1,"ks":{"o":{"a":0,"k":100,"ix":11},"r":{"a":0,"k":0,"ix":10},"p":{"a":0,"k":[408.818,443.727,0],"ix":2},"a":{"a":0,"k":[418.818,443.727,0],"ix":1},"s":{"a":1,"k":[{"i":{"x":[0.667,0.667,0.667],"y":[1,1,1]},"o":{"x":[0.333,0.333,0.333],"y":[0,0,0]},"t":0,"s":[0,0,100]},{"i":{"x":[0.667,0.667,0.667],"y":[1,1,1]},"o":{"x":[0.333,0.333,0.333],"y":[0,0,0]},"t":7,"s":[110,110,100]},{"i":{"x":[0.667,0.667,0.667],"y":[1,1,1]},"o":{"x":[0.333,0.333,0.333],"y":[0,0,0]},"t":10,"s":[100,100,100]},{"i":{"x":[0.667,0.667,0.667],"y":[1,1,1]},"o":{"x":[0.333,0.333,0.333],"y":[0,0,0]},"t":49,"s":[100,100,100]},{"i":{"x":[0.667,0.667,0.667],"y":[1,1,1]},"o":{"x":[0.333,0.333,0.333],"y":[0,0,0]},"t":52,"s":[110,110,100]},{"t":62,"s":[0,0,100]}],"ix":6}},"ao":0,"shapes":[{"ty":"gr","it":[{"ind":0,"ty":"sh","ix":1,"ks":{"a":0,"k":{"i":[[0,0],[0,0],[-3.213,0],[-1.007,0.755],[0,0],[0,0],[-1.928,2.571],[0,1.259],[0,0]],"o":[[0,0],[0,3.213],[1.259,0],[0,0],[0,0],[2.571,1.928],[0.755,-1.007],[0,0],[0,0]],"v":[[-29.091,-40.727],[-29.091,34.909],[-23.273,40.727],[-19.782,39.563],[0,24.727],[19.782,39.563],[27.927,38.4],[29.091,34.909],[29.091,-40.727]],"c":true},"ix":2},"nm":"Path 1","mn":"ADBE Vector Shape - Group","hd":false},{"ty":"fl","c":{"a":0,"k":[0.956862747669,0.572549045086,0.152941182256,1],"ix":4},"o":{"a":0,"k":100,"ix":5},"r":1,"bm":0,"nm":"Fill 1","mn":"ADBE Vector Graphic - Fill","hd":false},{"ty":"tr","p":{"a":0,"k":[418.818,403],"ix":2},"a":{"a":0,"k":[0,0],"ix":1},"s":{"a":0,"k":[100,100],"ix":3},"r":{"a":0,"k":0,"ix":6},"o":{"a":0,"k":100,"ix":7},"sk":{"a":0,"k":0,"ix":4},"sa":{"a":0,"k":0,"ix":5},"nm":"Transform"}],"nm":"Group 1","np":2,"cix":2,"bm":0,"ix":1,"mn":"ADBE Vector Group","hd":false},{"ty":"gr","it":[{"ind":0,"ty":"sh","ix":1,"ks":{"a":0,"k":{"i":[[3.213,0],[0,0],[0,0],[0,0],[0,0]],"o":[[0,0],[0,0],[0,0],[0,0],[0,-3.213]],"v":[[32,-26.182],[-37.818,-26.182],[-37.818,26.182],[37.818,26.182],[37.818,-20.364]],"c":true},"ix":2},"nm":"Path 1","mn":"ADBE Vector Shape - Group","hd":false},{"ty":"fl","c":{"a":0,"k":[1,0.713725507259,0.333333343267,1],"ix":4},"o":{"a":0,"k":100,"ix":5},"r":1,"bm":0,"nm":"Fill 1","mn":"ADBE Vector Graphic - Fill","hd":false},{"ty":"tr","p":{"a":0,"k":[474.091,388.455],"ix":2},"a":{"a":0,"k":[0,0],"ix":1},"s":{"a":0,"k":[100,100],"ix":3},"r":{"a":0,"k":0,"ix":6},"o":{"a":0,"k":100,"ix":7},"sk":{"a":0,"k":0,"ix":4},"sa":{"a":0,"k":0,"ix":5},"nm":"Transform"}],"nm":"Group 2","np":2,"cix":2,"bm":0,"ix":2,"mn":"ADBE Vector Group","hd":false},{"ty":"gr","it":[{"ind":0,"ty":"sh","ix":1,"ks":{"a":0,"k":{"i":[[0,-3.213],[0,0],[0,0],[0,0],[0,0]],"o":[[0,0],[0,0],[0,0],[0,0],[-3.213,0]],"v":[[-37.818,-20.364],[-37.818,26.182],[37.818,26.182],[37.818,-26.182],[-32,-26.182]],"c":true},"ix":2},"nm":"Path 1","mn":"ADBE Vector Shape - Group","hd":false},{"ty":"fl","c":{"a":0,"k":[1,0.713725507259,0.333333343267,1],"ix":4},"o":{"a":0,"k":100,"ix":5},"r":1,"bm":0,"nm":"Fill 1","mn":"ADBE Vector Graphic - Fill","hd":false},{"ty":"tr","p":{"a":0,"k":[363.545,388.455],"ix":2},"a":{"a":0,"k":[0,0],"ix":1},"s":{"a":0,"k":[100,100],"ix":3},"r":{"a":0,"k":0,"ix":6},"o":{"a":0,"k":100,"ix":7},"sk":{"a":0,"k":0,"ix":4},"sa":{"a":0,"k":0,"ix":5},"nm":"Transform"}],"nm":"Group 3","np":2,"cix":2,"bm":0,"ix":3,"mn":"ADBE Vector Group","hd":false},{"ty":"gr","it":[{"ind":0,"ty":"sh","ix":1,"ks":{"a":0,"k":{"i":[[3.213,0],[0,0],[0,3.213],[-3.213,0],[0,0],[0,-3.213]],"o":[[0,0],[-3.213,0],[0,-3.213],[0,0],[3.213,0],[0,3.213]],"v":[[11.636,5.818],[-11.636,5.818],[-17.455,0],[-11.636,-5.818],[11.636,-5.818],[17.455,0]],"c":true},"ix":2},"nm":"Path 1","mn":"ADBE Vector Shape - Group","hd":false},{"ty":"fl","c":{"a":0,"k":[1,0.713725507259,0.333333343267,1],"ix":4},"o":{"a":0,"k":100,"ix":5},"r":1,"bm":0,"nm":"Fill 1","mn":"ADBE Vector Graphic - Fill","hd":false},{"ty":"tr","p":{"a":0,"k":[360.636,501.909],"ix":2},"a":{"a":0,"k":[0,0],"ix":1},"s":{"a":0,"k":[100,100],"ix":3},"r":{"a":0,"k":0,"ix":6},"o":{"a":0,"k":100,"ix":7},"sk":{"a":0,"k":0,"ix":4},"sa":{"a":0,"k":0,"ix":5},"nm":"Transform"}],"nm":"Group 4","np":2,"cix":2,"bm":0,"ix":4,"mn":"ADBE Vector Group","hd":false},{"ty":"gr","it":[{"ind":0,"ty":"sh","ix":1,"ks":{"a":0,"k":{"i":[[3.213,0],[0,0],[0,3.213],[-3.213,0],[0,0],[0,-3.213]],"o":[[0,0],[-3.213,0],[0,-3.213],[0,0],[3.213,0],[0,3.213]],"v":[[26.182,5.818],[-26.182,5.818],[-32,0],[-26.182,-5.818],[26.182,-5.818],[32,0]],"c":true},"ix":2},"nm":"Path 1","mn":"ADBE Vector Shape - Group","hd":false},{"ty":"fl","c":{"a":0,"k":[1,0.713725507259,0.333333343267,1],"ix":4},"o":{"a":0,"k":100,"ix":5},"r":1,"bm":0,"nm":"Fill 1","mn":"ADBE Vector Graphic - Fill","hd":false},{"ty":"tr","p":{"a":0,"k":[375.182,484.455],"ix":2},"a":{"a":0,"k":[0,0],"ix":1},"s":{"a":0,"k":[100,100],"ix":3},"r":{"a":0,"k":0,"ix":6},"o":{"a":0,"k":100,"ix":7},"sk":{"a":0,"k":0,"ix":4},"sa":{"a":0,"k":0,"ix":5},"nm":"Transform"}],"nm":"Group 5","np":2,"cix":2,"bm":0,"ix":5,"mn":"ADBE Vector Group","hd":false},{"ty":"gr","it":[{"ind":0,"ty":"sh","ix":1,"ks":{"a":0,"k":{"i":[[-3.213,0],[0,0],[0,-3.213],[0,0],[3.213,0],[0,0],[0,3.213],[0,0]],"o":[[0,0],[3.213,0],[0,0],[0,3.213],[0,0],[-3.213,0],[0,0],[0,-3.213]],"v":[[-87.273,-81.455],[87.273,-81.455],[93.091,-75.636],[93.091,75.636],[87.273,81.455],[-87.273,81.455],[-93.091,75.636],[-93.091,-75.636]],"c":true},"ix":2},"nm":"Path 1","mn":"ADBE Vector Shape - Group","hd":false},{"ty":"fl","c":{"a":0,"k":[0.988235294819,0.800000011921,0.592156887054,1],"ix":4},"o":{"a":0,"k":100,"ix":5},"r":1,"bm":0,"nm":"Fill 1","mn":"ADBE Vector Graphic - Fill","hd":false},{"ty":"tr","p":{"a":0,"k":[418.818,443.727],"ix":2},"a":{"a":0,"k":[0,0],"ix":1},"s":{"a":0,"k":[100,100],"ix":3},"r":{"a":0,"k":0,"ix":6},"o":{"a":0,"k":100,"ix":7},"sk":{"a":0,"k":0,"ix":4},"sa":{"a":0,"k":0,"ix":5},"nm":"Transform"}],"nm":"Group 6","np":2,"cix":2,"bm":0,"ix":6,"mn":"ADBE Vector Group","hd":false}],"ip":0,"op":75,"st":0,"bm":0},{"ddd":0,"ind":5,"ty":4,"nm":"bg 2","td":1,"sr":1,"ks":{"o":{"a":0,"k":100,"ix":11},"r":{"a":0,"k":0,"ix":10},"p":{"a":0,"k":[263.364,275,0],"ix":2},"a":{"a":0,"k":[0,0,0],"ix":1},"s":{"a":0,"k":[100,100,100],"ix":6}},"ao":0,"shapes":[{"ty":"gr","it":[{"ind":0,"ty":"sh","ix":1,"ks":{"a":0,"k":{"i":[[-99.612,0],[0,-99.612],[99.612,0],[0,99.612]],"o":[[99.612,0],[0,99.612],[-99.612,0],[0,-99.612]],"v":[[0,-180.364],[180.364,0],[0,180.364],[-180.364,0]],"c":true},"ix":2},"nm":"Path 1","mn":"ADBE Vector Shape - Group","hd":false},{"ty":"fl","c":{"a":0,"k":[0.701960802078,0.847058832645,0.956862747669,1],"ix":4},"o":{"a":0,"k":100,"ix":5},"r":1,"bm":0,"nm":"Fill 1","mn":"ADBE Vector Graphic - Fill","hd":false},{"ty":"tr","p":{"a":0,"k":[0,0],"ix":2},"a":{"a":0,"k":[0,0],"ix":1},"s":{"a":0,"k":[100,100],"ix":3},"r":{"a":0,"k":0,"ix":6},"o":{"a":0,"k":100,"ix":7},"sk":{"a":0,"k":0,"ix":4},"sa":{"a":0,"k":0,"ix":5},"nm":"Transform"}],"nm":"Group 1","np":2,"cix":2,"bm":0,"ix":1,"mn":"ADBE Vector Group","hd":false}],"ip":0,"op":75,"st":0,"bm":0},{"ddd":0,"ind":6,"ty":4,"nm":"map","tt":1,"sr":1,"ks":{"o":{"a":0,"k":100,"ix":11},"r":{"a":0,"k":0,"ix":10},"p":{"a":1,"k":[{"i":{"x":0.833,"y":0.833},"o":{"x":0.167,"y":0.167},"t":0,"s":[-469.732,308.588,0],"to":[157.5,0,0],"ti":[-157.5,0,0]},{"t":75,"s":[475.268,308.588,0]}],"ix":2},"a":{"a":0,"k":[-459.732,308.588,0],"ix":1},"s":{"a":0,"k":[100,100,100],"ix":6}},"ao":0,"shapes":[{"ty":"gr","it":[{"ty":"gr","it":[{"ty":"gr","it":[{"ind":0,"ty":"sh","ix":1,"ks":{"a":0,"k":{"i":[[0,0],[-0.438,0],[0,0],[0,0],[0,0]],"o":[[0,0],[0.438,0],[0,0],[0,0],[0,0]],"v":[[-20.25,-182.139],[-14.433,-183.055],[-14.433,-177.696],[-26.545,-176.919],[-28.856,-179.688]],"c":true},"ix":2},"nm":"Path 1","mn":"ADBE Vector Shape - Group","hd":false},{"ind":1,"ty":"sh","ix":2,"ks":{"a":0,"k":{"i":[[0,0],[0,0],[0,0],[0,0],[0,0],[0,0],[0,0],[0,0]],"o":[[0,0],[0,0],[0,0],[0,0],[0,0],[0,0],[0,0],[0,0]],"v":[[-28.836,-194.091],[-28.836,-194.55],[-23.457,-194.55],[-22.999,-196.382],[-14.214,-196.382],[-14.214,-192.557],[-16.724,-189.191],[-28.836,-189.191]],"c":true},"ix":2},"nm":"Path 2","mn":"ADBE Vector Shape - Group","hd":false},{"ind":2,"ty":"sh","ix":3,"ks":{"a":0,"k":{"i":[[0,0],[0,0],[0,0],[0,0],[0,0]],"o":[[0,0],[0,0],[0,0],[0,0],[0,0]],"v":[[0.289,-156.998],[6.106,-155.624],[4.094,-147.795],[-2.181,-145.803],[-6.166,-153.93]],"c":true},"ix":2},"nm":"Path 3","mn":"ADBE Vector Shape - Group","hd":false},{"ind":3,"ty":"sh","ix":4,"ks":{"a":0,"k":{"i":[[0,0],[0,0],[0,0],[0,0],[0,0]],"o":[[0,0],[0,0],[0,0],[0,0],[0,0]],"v":[[7.799,-122.355],[13.477,-128.491],[21.604,-128.491],[11.186,-113.929],[6.883,-116.24]],"c":true},"ix":2},"nm":"Path 4","mn":"ADBE Vector Shape - Group","hd":false},{"ind":4,"ty":"sh","ix":5,"ks":{"a":0,"k":{"i":[[0,0],[0,0],[0,0],[0,0],[0,0],[0,0],[0,0],[0,0]],"o":[[0,0],[0,0],[0,0],[0,0],[0,0],[0,0],[0,0],[0,0]],"v":[[9.174,-135.523],[16.226,-138.432],[25.887,-138.432],[25.887,-135.523],[28.019,-135.523],[28.019,-130.463],[13.317,-130.463],[7.799,-131.997]],"c":true},"ix":2},"nm":"Path 5","mn":"ADBE Vector Shape - Group","hd":false},{"ind":5,"ty":"sh","ix":6,"ks":{"a":0,"k":{"i":[[0,0],[0,0],[0,0]],"o":[[0,0],[0,0],[0,0]],"v":[[30.629,-136.3],[35.689,-131.698],[30.629,-130.463]],"c":true},"ix":2},"nm":"Path 6","mn":"ADBE Vector Shape - Group","hd":false},{"ind":6,"ty":"sh","ix":7,"ks":{"a":0,"k":{"i":[[0,0],[0,0],[0,0],[0,0],[0,0],[0,0]],"o":[[0,0],[0,0],[0,0],[0,0],[0,0],[0,0]],"v":[[36.784,-123.112],[37.402,-123.112],[46.745,-120.343],[46.745,-115.582],[38.916,-115.582],[36.784,-118.67]],"c":true},"ix":2},"nm":"Path 7","mn":"ADBE Vector Shape - Group","hd":false},{"ind":7,"ty":"sh","ix":8,"ks":{"a":0,"k":{"i":[[0,0],[0,0],[0,0],[0,0]],"o":[[0,0],[0,0],[0,0],[0,0]],"v":[[41.745,-129.248],[45.51,-126.898],[42.502,-124.407],[39.533,-126.898]],"c":true},"ix":2},"nm":"Path 8","mn":"ADBE Vector Shape - Group","hd":false},{"ind":8,"ty":"sh","ix":9,"ks":{"a":0,"k":{"i":[[0,0],[0,0],[0,0],[0,0.777],[0,0],[0,0]],"o":[[0,0],[0,0],[0,0],[0,0],[0,0],[0,0]],"v":[[34.792,-123.571],[31.107,-121.2],[26.525,-120.363],[26.525,-128.491],[34.812,-128.491],[34.792,-123.571]],"c":true},"ix":2},"nm":"Path 9","mn":"ADBE Vector Shape - Group","hd":false},{"ind":9,"ty":"sh","ix":10,"ks":{"a":0,"k":{"i":[[0,0],[0,0],[0,0],[0,0],[0,0],[0,0],[0,0]],"o":[[0,0],[0,0],[0,0],[0,0],[0,0],[0,0],[0,0]],"v":[[32.94,-113.909],[29.414,-110.383],[21.585,-110.383],[22.82,-115.742],[26.505,-116.06],[27.282,-117.893],[32.94,-118.67]],"c":true},"ix":2},"nm":"Path 10","mn":"ADBE Vector Shape - Group","hd":false},{"ind":10,"ty":"sh","ix":11,"ks":{"a":0,"k":{"i":[[0,0],[0,0],[0,0],[0,0],[0,0],[0,0],[0,0],[0,0],[0,0],[0,0],[0,0],[0,0],[0,0],[0,0],[0,0],[0,0],[0,0],[0,0],[0,0],[0,0],[0,0],[0,0],[0,0],[0,0],[0,0],[0,0],[0,0],[0,0],[0,0],[0,0],[0,0],[0,0],[0,0],[0,0],[0,0],[0,0],[0,0],[0,0],[0,0],[0,0],[0,0],[0,0],[0,0],[0,0],[0,0],[0,0],[0,0],[0,0],[0,0],[0,0],[0,0],[0,0],[0,0],[0,0],[0,0],[0,0],[0,0],[-0.02,-0.1],[0,0],[0,0],[0,0],[0,0],[0,0],[0,0],[0,0],[0,0],[0,0],[0,0],[0,0],[0,0],[0,0],[0,0],[0,0],[0,0],[0,0],[0,0],[0,0],[0,0],[0,0],[0,0],[0,0],[0,0],[0,0],[0,0],[0,0],[0,0],[0,0],[0,0],[0,0],[0,0],[0,0],[0,0],[0,0],[0,0],[0,0],[0,0],[0,0],[0,0],[0,0],[0,0],[0,0],[0,0],[0,0],[0,0],[0,0],[0,0],[0,0],[0,0],[0,0],[0,0],[0,0],[0,0],[0,0],[0,0],[0,0],[0,0],[0,0],[0.598,0],[0,0],[0,0],[0,0],[0,0],[0,0],[0,0],[0,0],[0,0],[0,0],[0,0],[0,0],[0,0],[0,0],[0,0],[0,0],[0,0],[0,0],[0,0],[0,0],[0,0],[0,0],[0,0],[0,0],[0,0],[0,0],[0,0],[0,0],[0,0],[0,0],[0,0],[0,0],[0,0],[0,0],[0,0],[0,0],[0,0],[0,0],[0,0],[0,0],[0,0],[0,0],[0,0],[0,0],[0,0],[0,0],[0,0],[0,0],[0,0],[0,0],[0,0],[0,0],[0,0],[0,0],[0,0],[0,0],[0,0],[0,0],[0,0],[0,0],[0,0],[0,0],[0,0],[0,0],[0,0],[0,0],[0,0],[0,0],[-0.817,0],[0,0],[0,0],[0,0],[0,0],[0,0],[0,0],[0,0],[0,0],[0,0],[0,0],[0,0],[0,0],[0,0],[0,0],[0,0],[0,0],[0,0],[0,0],[0,0],[0,0],[0,0],[0,0],[0,0],[0,0],[0,0],[0,0],[0,0],[0,0],[0,0],[0,0],[0,0],[0,0]],"o":[[0,0],[0,0],[0,0],[0,0],[0,0],[0,0],[0,0],[0,0],[0,0],[0,0],[0,0],[0,0],[0,0],[0,0],[0,0],[0,0],[0,0],[0,0],[0,0],[0,0],[0,0],[0,0],[0,0],[0,0],[0,0],[0,0],[0,0],[0,0],[0,0],[0,0],[0,0],[0,0],[0,0],[0,0],[0,0],[0,0],[0,0],[0,0],[0,0],[0,0],[0,0],[0,0],[0,0],[0,0],[0,0],[0,0],[0,0],[0,0],[0,0],[0,0],[0,0],[0,0],[0,0],[0,0],[0,0],[0,0],[0,0],[0,0],[0,0],[0,0],[0,0],[0,0],[0,0],[0,0],[0,0],[0,0],[0,0],[0,0],[0,0],[0,0],[0,0],[0,0],[0,0],[0,0],[0,0],[0,0],[0,0],[0,0],[0,0],[0,0],[0,0],[0,0],[0,0],[0,0],[0,0],[0,0],[0,0],[0,0],[0,0],[0,0],[0,0],[0,0],[0,0],[0,0],[0,0],[0,0],[0,0],[0,0],[0,0],[0,0],[0,0],[0,0],[0,0],[0,0],[0,0],[0,0],[0,0],[0,0],[0,0],[0,0],[0,0],[0,0],[0,0],[0,0],[0,0],[0,0],[0,0],[-0.598,0],[0,0],[0,0],[0,0],[0,0],[0,0],[0,0],[0,0],[0,0],[0,0],[0,0],[0,0],[0,0],[0,0],[0,0],[0,0],[0,0],[0,0],[0,0],[0,0],[0,0],[0,0],[0,0],[0,0],[0,0],[0,0],[0,0],[0,0],[0,0],[0,0],[0,0],[0,0],[0,0],[0,0],[0,0],[0,0],[0,0],[0,0],[0,0],[0,0],[0,0],[0,0],[0,0],[0,0],[0,0],[0,0],[0,0],[0,0],[0,0],[0,0],[0,0],[0,0],[0,0],[0,0],[0,0],[0,0],[0,0],[0,0],[0,0],[0,0],[0,0],[0,0],[0,0],[0,0],[0,0],[0,0],[0,0],[0,0],[0.817,0],[0,0],[0,0],[0,0],[0,0],[0,0],[0,0],[0,0],[0,0],[0,0],[0,0],[0,0],[0,0],[0,0],[0,0],[0,0],[0,0],[0,0],[0,0],[0,0],[0,0],[0,0],[0,0],[0,0],[0,0],[0,0],[0,0],[0,0],[0,0],[0,0],[0,0],[0,0],[0,0]],"v":[[144.02,37.173],[122.365,36.954],[105.193,30.439],[104.377,18.188],[98.639,8.148],[83.121,7.929],[74.116,-6.156],[66.148,-10.04],[65.73,-5.757],[51.207,-4.901],[45.888,-12.291],[30.768,-15.359],[18.337,-0.956],[-1.285,-4.263],[-2.719,-26.376],[-17.023,-28.826],[-11.285,-39.663],[-12.939,-45.898],[-31.744,-33.328],[-43.577,-34.762],[-47.821,-44.006],[-45.231,-53.548],[-38.697,-65.58],[-23.676,-73.19],[5.349,-73.19],[5.269,-64.345],[15.688,-59.484],[14.851,-74.605],[22.361,-82.155],[37.541,-92.115],[38.577,-99.128],[53.697,-114.865],[69.774,-123.77],[68.359,-124.945],[79.256,-135.205],[83.24,-134.149],[85.073,-131.858],[89.217,-136.44],[90.233,-136.878],[85.691,-137.515],[81.109,-139.049],[81.109,-143.492],[83.559,-145.484],[88.938,-145.484],[91.408,-144.408],[93.54,-140.125],[96.149,-140.524],[96.149,-140.902],[96.906,-140.643],[104.436,-141.818],[105.512,-145.504],[109.795,-144.428],[109.795,-140.444],[105.811,-137.695],[105.811,-137.695],[106.389,-133.312],[120.055,-129.109],[120.094,-128.949],[123.222,-129.228],[123.441,-135.145],[112.564,-140.025],[111.947,-142.874],[120.931,-145.942],[121.33,-154.528],[111.947,-160.245],[111.329,-174.748],[98.46,-168.413],[93.759,-168.413],[94.994,-179.449],[77.463,-183.593],[70.212,-178.115],[70.212,-161.401],[57.184,-157.257],[51.964,-146.38],[46.307,-145.464],[46.307,-159.409],[34.055,-161.102],[27.919,-165.086],[25.449,-174.13],[47.382,-186.96],[58.12,-190.227],[59.196,-183.015],[65.172,-183.334],[65.63,-186.96],[71.885,-187.856],[71.985,-189.111],[69.296,-190.227],[68.678,-194.052],[76.368,-194.689],[81.009,-199.53],[81.268,-199.888],[81.328,-199.868],[82.742,-201.323],[98.898,-203.375],[106.03,-197.299],[87.304,-187.338],[111.13,-181.72],[114.218,-189.689],[124.636,-189.689],[128.322,-196.641],[120.951,-198.474],[120.951,-207.259],[97.863,-217.479],[81.926,-215.646],[72.921,-210.945],[73.539,-199.49],[64.136,-200.924],[62.682,-207.259],[71.686,-215.447],[55.331,-216.284],[50.63,-214.849],[48.578,-209.331],[54.713,-208.295],[53.478,-202.159],[43.059,-201.542],[41.426,-197.458],[26.306,-197.06],[25.29,-205.646],[37.143,-205.845],[46.147,-214.63],[41.227,-217.08],[34.693,-210.745],[23.836,-211.363],[17.301,-220.367],[3.397,-220.367],[-11.126,-209.53],[2.161,-209.53],[3.377,-205.646],[-0.09,-202.379],[14.632,-201.96],[16.883,-196.641],[0.309,-197.259],[-0.508,-201.343],[-10.927,-203.594],[-16.445,-206.662],[-40.968,-206.462],[-48.538,-199.112],[-53.638,-199.53],[-59.355,-202.797],[-76.328,-207.897],[-107.405,-207.897],[-125.354,-195.625],[-137.406,-193.773],[-142.924,-189.49],[-134.338,-188.215],[-134.338,-184.788],[-152.725,-184.788],[-159.897,-179.688],[-150.713,-171.919],[-125.573,-171.72],[-122.106,-175.405],[-101.05,-175.405],[-93.5,-168.652],[-93.898,-158.233],[-87.563,-152.317],[-92.882,-148.552],[-91.647,-134.746],[-110.652,-111.658],[-110.652,-90.004],[-100.432,-85.083],[-100.432,-65.62],[-90.631,-48.906],[-82.663,-47.671],[-81.647,-53.409],[-91.049,-67.931],[-92.882,-82.035],[-87.364,-82.035],[-85.033,-67.513],[-71.427,-47.691],[-74.953,-41.277],[-66.307,-28.069],[-44.852,-22.75],[-44.852,-26.216],[-36.266,-24.981],[-37.083,-18.845],[-30.35,-17.61],[-19.931,-14.761],[-5.209,2.012],[13.576,3.426],[15.409,18.766],[2.54,27.77],[1.922,41.496],[0.09,49.863],[18.696,73.17],[20.13,81.139],[27.7,82.971],[42.82,93.789],[42.82,135.882],[47.92,137.316],[44.434,156.739],[53.02,168.174],[51.426,187.438],[62.761,207.359],[77.324,220.089],[91.966,220.367],[93.4,215.666],[82.643,206.602],[83.26,202.1],[85.193,196.601],[85.611,190.964],[78.34,190.765],[74.674,186.183],[80.71,180.366],[81.527,175.943],[74.794,174.011],[75.192,169.947],[84.794,168.473],[99.416,161.441],[104.317,152.436],[119.656,132.834],[116.17,117.475],[120.871,109.327],[134.976,109.745],[144.478,102.235],[147.546,72.652],[158.064,59.265],[159.897,50.659],[150.295,47.611]],"c":true},"ix":2},"nm":"Path 11","mn":"ADBE Vector Shape - Group","hd":false},{"ty":"fl","c":{"a":0,"k":[0.364705890417,0.858823537827,0.482352942228,1],"ix":4},"o":{"a":0,"k":100,"ix":5},"r":1,"bm":0,"nm":"Fill 1","mn":"ADBE Vector Graphic - Fill","hd":false},{"ty":"tr","p":{"a":0,"k":[-1242.809,310.77],"ix":2},"a":{"a":0,"k":[0,0],"ix":1},"s":{"a":0,"k":[100,100],"ix":3},"r":{"a":0,"k":0,"ix":6},"o":{"a":0,"k":100,"ix":7},"sk":{"a":0,"k":0,"ix":4},"sa":{"a":0,"k":0,"ix":5},"nm":"Transform"}],"nm":"Group 1","np":12,"cix":2,"bm":0,"ix":1,"mn":"ADBE Vector Group","hd":false},{"ty":"gr","it":[{"ind":0,"ty":"sh","ix":1,"ks":{"a":0,"k":{"i":[[0,0],[0,0],[0,0],[0,0],[0,0]],"o":[[0,0],[0,0],[0,0],[0,0],[0,0]],"v":[[-2.829,3.207],[2.291,2.769],[2.829,-0.797],[-0.239,-3.207],[-2.55,-0.359]],"c":true},"ix":2},"nm":"Path 1","mn":"ADBE Vector Shape - Group","hd":false},{"ty":"fl","c":{"a":0,"k":[0.364705890417,0.858823537827,0.482352942228,1],"ix":4},"o":{"a":0,"k":100,"ix":5},"r":1,"bm":0,"nm":"Fill 1","mn":"ADBE Vector Graphic - Fill","hd":false},{"ty":"tr","p":{"a":0,"k":[-1163.174,187.079],"ix":2},"a":{"a":0,"k":[0,0],"ix":1},"s":{"a":0,"k":[100,100],"ix":3},"r":{"a":0,"k":0,"ix":6},"o":{"a":0,"k":100,"ix":7},"sk":{"a":0,"k":0,"ix":4},"sa":{"a":0,"k":0,"ix":5},"nm":"Transform"}],"nm":"Group 2","np":2,"cix":2,"bm":0,"ix":2,"mn":"ADBE Vector Group","hd":false},{"ty":"gr","it":[{"ind":0,"ty":"sh","ix":1,"ks":{"a":0,"k":{"i":[[0,0],[0,0],[0,0],[0,0],[-0.139,-1.016],[0,0],[0,0],[0,0],[0,0],[0,0],[0,0],[0,0]],"o":[[0,0],[0,0],[0,0],[0,0],[0,0],[0,0],[0,0],[0,0],[0,0],[0,0],[0,0],[0,0]],"v":[[-0.199,-0.807],[-7.251,-0.807],[-7.251,2.819],[-5.578,2.819],[-5.339,4.612],[-1.016,4.253],[1.673,2.58],[2.391,-0.807],[5.877,-1.106],[7.251,-3.954],[4.044,-4.612],[1.235,-4.552]],"c":true},"ix":2},"nm":"Path 1","mn":"ADBE Vector Shape - Group","hd":false},{"ty":"fl","c":{"a":0,"k":[0.364705890417,0.858823537827,0.482352942228,1],"ix":4},"o":{"a":0,"k":100,"ix":5},"r":1,"bm":0,"nm":"Fill 1","mn":"ADBE Vector Graphic - Fill","hd":false},{"ty":"tr","p":{"a":0,"k":[-1148.811,184.679],"ix":2},"a":{"a":0,"k":[0,0],"ix":1},"s":{"a":0,"k":[100,100],"ix":3},"r":{"a":0,"k":0,"ix":6},"o":{"a":0,"k":100,"ix":7},"sk":{"a":0,"k":0,"ix":4},"sa":{"a":0,"k":0,"ix":5},"nm":"Transform"}],"nm":"Group 3","np":2,"cix":2,"bm":0,"ix":3,"mn":"ADBE Vector Group","hd":false},{"ty":"gr","it":[{"ind":0,"ty":"sh","ix":1,"ks":{"a":0,"k":{"i":[[0,0],[0,0],[0,0],[0,0],[0,0],[0,0],[0,0],[0,0],[0,0],[0,0],[0,0],[0,0],[0,0],[0,0],[0,0],[0,0],[0,0],[0,0],[0,0],[0,0]],"o":[[0,0],[0,0],[0,0],[0,0],[0,0],[0,0],[0,0],[0,0],[0,0],[0,0],[0,0],[0,0],[0,0],[0,0],[0,0],[0,0],[0,0],[0,0],[0,0],[0,0]],"v":[[-44.235,-60.212],[-47.004,-57.562],[-53.419,-58.08],[-54.654,-60.012],[-64.773,-60.729],[-64.056,-63.997],[-58.717,-68.598],[-58.717,-72.463],[-68.957,-79.933],[-69.375,-89.436],[-67.303,-94.137],[-59.036,-94.854],[-51.984,-91.906],[-51.665,-86.985],[-61.666,-87.543],[-62.184,-82.981],[-49.613,-74.595],[-49.613,-68.459],[-44.195,-64.475],[-44.195,-60.211]],"c":true},"ix":2},"nm":"Path 1","mn":"ADBE Vector Shape - Group","hd":false},{"ind":1,"ty":"sh","ix":2,"ks":{"a":0,"k":{"i":[[0,0],[0,0],[0,0],[0,0],[0,0],[0,0],[0,0],[0,0],[0,0],[0,0],[0,0],[0,0]],"o":[[0,0],[0,0],[0,0],[0,0],[0,0],[0,0],[0,0],[0,0],[0,0],[0,0],[0,0],[0,0]],"v":[[-105.313,-67.981],[-121.21,-68.638],[-125.971,-67.981],[-125.971,-78.838],[-122.385,-82.842],[-118.561,-84.037],[-110.094,-85.013],[-108.261,-87.902],[-104.795,-86.189],[-104.337,-76.288],[-95.074,-72.503],[-94.257,-67.981]],"c":true},"ix":2},"nm":"Path 2","mn":"ADBE Vector Shape - Group","hd":false},{"ind":2,"ty":"sh","ix":3,"ks":{"a":0,"k":{"i":[[0,0],[0,0],[0,0],[0,0],[0,0],[0,0],[0,0],[0,0],[0,0],[0,0],[0,0],[0,0]],"o":[[0,0],[0,0],[0,0],[0,0],[0,0],[0,0],[0,0],[0,0],[0,0],[0,0],[0,0],[0,0]],"v":[[-142.805,-153.203],[-154.976,-145.753],[-154.976,-140.852],[-148.064,-137.625],[-147.625,-131.031],[-157.347,-116.548],[-174.22,-116.708],[-175.276,-120.234],[-164.718,-125.593],[-164.638,-145.593],[-146.709,-158.084],[-142.805,-158.084]],"c":true},"ix":2},"nm":"Path 3","mn":"ADBE Vector Shape - Group","hd":false},{"ind":3,"ty":"sh","ix":4,"ks":{"a":0,"k":{"i":[[0,0],[0,0],[0,0],[0,0],[0,0],[0,0],[0,0],[0,0],[0,0],[0,0],[0,0],[0,0],[0,0],[0,0],[0,0],[0,0],[0,0],[0,0],[0,0],[0,0],[0,0],[0,0],[0,0],[0,0],[0,0],[0,0],[0,0],[0,0],[0,0],[0,0],[0,0],[0,0],[0,0],[0,0],[0,0],[0,0],[0,0],[0,0],[0,0],[0,0],[0,0],[0,0],[0,0],[0,0],[0,0],[0,0],[0,0],[0,0],[0,0],[0,0],[0,0],[0,0],[0,0],[0,0],[0,0],[0,0],[0,0],[0,0],[0,0],[0,0],[0,0],[0,0],[0,0],[0,0],[0,0],[0,0],[0,0],[0,0],[0,0],[0,0],[0,0],[0,0],[0,0],[0,0],[0,0],[0,0],[0,0],[0,0],[0,0],[0,0],[0,0],[0,0],[0,0],[0,0],[0,0],[0,0],[0,0],[0,0],[0,0],[0,0],[0,0],[0,0],[0,0],[0,0],[0,0],[0,0],[0,0],[0,0],[0,0],[0,0],[0,0],[0,0],[0,0],[0,0],[0,0],[0,0],[0,0],[0,0],[0,0],[0,0],[0,0],[0,0],[0,0],[0,0],[0,0],[0,0],[0,0],[0,0],[0,0],[0,0],[0,0],[0,0],[0,0],[0,0],[0,0],[0,0],[0,0],[0,0],[0,0],[0,0],[0,0],[0,0],[0,0],[0,0],[0,0],[0,0],[0,0],[0,0],[0,0],[0,0],[0,0],[0,0],[0,0],[0,0],[0,0],[0,0],[0,0],[0,0],[0,0],[0,0],[0,0],[0,0],[0,0],[0,0],[0,0],[0,0],[0,0],[0,0],[0,0],[0,0],[0,0],[0,0],[0,0],[0,0],[0,0],[0,0],[0,0],[0,0],[0,0],[0,0],[0,0],[0,0],[0,0],[0,0],[0,0],[0,0],[0,0],[0,0],[0,0],[0,0],[0,0],[0,0],[0,0],[0,0],[0,0],[0,0],[0,0],[0,0],[0,0],[0,0],[0,0],[0,0],[0,0],[0,0],[0,0],[0,0],[0,0],[0,0],[0,0],[0,0.637],[0,0],[0,0],[0,0],[0,0],[0,0],[0,0],[0,0],[0,0],[0,0],[0,0],[0,0],[0,0],[0,0],[0,0],[0,0],[0,0],[0,0],[0,0]],"o":[[0,0],[0,0],[0,0],[0,0],[0,0],[0,0],[0,0],[0,0],[0,0],[0,0],[0,0],[0,0],[0,0],[0,0],[0,0],[0,0],[0,0],[0,0],[0,0],[0,0],[0,0],[0,0],[0,0],[0,0],[0,0],[0,0],[0,0],[0,0],[0,0],[0,0],[0,0],[0,0],[0,0],[0,0],[0,0],[0,0],[0,0],[0,0],[0,0],[0,0],[0,0],[0,0],[0,0],[0,0],[0,0],[0,0],[0,0],[0,0],[0,0],[0,0],[0,0],[0,0],[0,0],[0,0],[0,0],[0,0],[0,0],[0,0],[0,0],[0,0],[0,0],[0,0],[0,0],[0,0],[0,0],[0,0],[0,0],[0,0],[0,0],[0,0],[0,0],[0,0],[0,0],[0,0],[0,0],[0,0],[0,0],[0,0],[0,0],[0,0],[0,0],[0,0],[0,0],[0,0],[0,0],[0,0],[0,0],[0,0],[0,0],[0,0],[0,0],[0,0],[0,0],[0,0],[0,0],[0,0],[0,0],[0,0],[0,0],[0,0],[0,0],[0,0],[0,0],[0,0],[0,0],[0,0],[0,0],[0,0],[0,0],[0,0],[0,0],[0,0],[0,0],[0,0],[0,0],[0,0],[0,0],[0,0],[0,0],[0,0],[0,0],[0,0],[0,0],[0,0],[0,0],[0,0],[0,0],[0,0],[0,0],[0,0],[0,0],[0,0],[0,0],[0,0],[0,0],[0,0],[0,0],[0,0],[0,0],[0,0],[0,0],[0,0],[0,0],[0,0],[0,0],[0,0],[0,0],[0,0],[0,0],[0,0],[0,0],[0,0],[0,0],[0,0],[0,0],[0,0],[0,0],[0,0],[0,0],[0,0],[0,0],[0,0],[0,0],[0,0],[0,0],[0,0],[0,0],[0,0],[0,0],[0,0],[0,0],[0,0],[0,0],[0,0],[0,0],[0,0],[0,0],[0,0],[0,0],[0,0],[0,0],[0,0],[0,0],[0,0],[0,0],[0,0],[0,0],[0,0],[0,0],[0,0],[0,0],[0,0],[0,0],[0,0],[0,0],[0,0],[0,0],[0,0],[0,0],[0,-0.657],[0,0],[0,0],[0,0],[0,0],[0,0],[0,0],[0,0],[0,0],[0,0],[0,0],[0,0],[0,0],[0,0],[0,0],[0,0],[0,0],[0,0],[0,0]],"v":[[111.528,40.848],[140.633,68.738],[142.187,63.837],[118.56,30.111],[121.011,20.29],[133.481,34.414],[140.434,35.151],[149.578,29.055],[148.064,19.871],[132.943,7.719],[132.346,-3.317],[136.669,-9.134],[144.318,-6.684],[143.701,-1.464],[148.084,5.269],[151.968,2.5],[149.837,-5.468],[171.312,-13.138],[180.694,-21.007],[179.28,-35.211],[160.594,-54.813],[160.275,-70.75],[168.563,-70.75],[194.301,-51.128],[201.552,-53.08],[196.751,-59.415],[182.965,-67.782],[183.782,-80.232],[200.117,-80.212],[201.432,-95.651],[195.177,-103.839],[198.882,-107.823],[206.831,-99.855],[209.381,-103.221],[199.161,-114.875],[173.742,-117.943],[170.355,-124.676],[177.706,-135.095],[183.523,-130.812],[200.994,-129.278],[223.067,-144],[226.752,-139.398],[221.832,-131.728],[221.832,-124.059],[242.071,-107.504],[248.526,-110.871],[246.076,-121.907],[231.653,-135.394],[250.657,-136.629],[250.657,-142.147],[259.861,-143.98],[252.809,-148.841],[253.128,-152.586],[272.451,-149.458],[276.137,-152.586],[250.1,-163.622],[155.056,-168.523],[146.171,-173.025],[132.067,-175.117],[121.449,-175.475],[111.847,-165.754],[107.803,-166.072],[94.994,-175.575],[57.283,-175.575],[39.792,-185.993],[4.751,-183.782],[-21.824,-171.889],[-21.604,-158.084],[-29.832,-155.634],[-31.665,-169.439],[-34.713,-174.24],[-43.916,-176.491],[-46.048,-168.204],[-43.279,-161.471],[-76.009,-163.602],[-91.607,-156.351],[-93.978,-163.184],[-97.862,-162.168],[-100.711,-154.618],[-108.899,-148.223],[-128.84,-148.781],[-129.736,-153.183],[-108.899,-154.1],[-104.616,-157.785],[-129.776,-169.439],[-160.455,-168.523],[-177.607,-159.737],[-184.041,-148.243],[-195.376,-143.801],[-200.157,-138.601],[-199.062,-132.545],[-193.225,-131.728],[-189.679,-122.923],[-179.599,-126.987],[-177.925,-115.194],[-180.973,-115.194],[-189.28,-116.429],[-198.464,-114.895],[-207.349,-102.325],[-220.078,-100.333],[-221.911,-89.456],[-216.532,-88.181],[-218.066,-81.189],[-230.716,-83.719],[-242.31,-81.189],[-244.761,-74.734],[-242.749,-61.208],[-235.936,-58.02],[-224.541,-58.08],[-216.831,-58.777],[-214.461,-64.913],[-202.428,-80.571],[-194.52,-78.937],[-186.711,-85.989],[-185.256,-80.471],[-166.052,-67.523],[-168.403,-64.375],[-177.069,-64.833],[-173.742,-60.112],[-168.423,-58.937],[-162.188,-61.546],[-162.307,-69.057],[-159.538,-70.451],[-161.769,-72.822],[-174.579,-79.953],[-177.945,-89.456],[-167.287,-89.456],[-163.901,-86.089],[-154.717,-78.2],[-154.319,-68.658],[-144.816,-58.538],[-141.29,-72.403],[-134.697,-75.989],[-133.461,-64.654],[-127.027,-57.602],[-107.604,-57.921],[-101.886,-53.618],[-101.886,-43.498],[-108.939,-37.063],[-128.561,-37.063],[-140.533,-45.968],[-153.084,-44.733],[-153.084,-37.063],[-157.088,-37.063],[-161.371,-40.131],[-183.145,-45.649],[-183.145,-59.753],[-210.736,-57.602],[-219.302,-53],[-230.258,-53],[-235.637,-53.538],[-248.944,-46.147],[-248.944,-32.242],[-276.137,-12.62],[-273.885,-4.253],[-268.367,-4.253],[-269.802,3.715],[-273.686,5.13],[-273.885,25.987],[-250.398,52.761],[-240.159,52.761],[-239.541,51.128],[-221.154,51.128],[-215.855,46.227],[-205.417,46.227],[-199.699,51.944],[-184.181,53.578],[-186.232,74.236],[-168.961,104.676],[-178.065,122.047],[-177.447,130.234],[-170.276,137.366],[-170.276,157.008],[-160.893,169.658],[-160.893,185.993],[-133.083,185.993],[-112.226,164.538],[-105.691,152.885],[-97.325,151.032],[-97.325,141.231],[-91.806,134.677],[-80.172,118.74],[-82.623,94.436],[-87.723,85.412],[-64.793,63.499],[-39.513,27.362],[-44.414,25.111],[-70.65,30.629],[-77.403,27.262],[-104.994,-24.712],[-103.062,-26.963],[-75.71,6.245],[-74.993,16.564],[-68.658,22.899],[-55.789,22.063],[-28.895,2.6],[-20.449,-2.918],[-20.628,-9.652],[-29.593,-10.827],[-61.068,-26.306],[-60.869,-39.035],[-53.916,-39.035],[-52.881,-30.25],[-38.298,-21.863],[-21.624,-21.047],[14.533,-15.13],[23.019,-9.791],[23.019,-1.504],[21.923,9.751],[40.49,40.231],[46.466,41.605],[52.442,32.94],[55.749,8.257],[61.945,-5.03],[71.905,-8.755],[89.496,-7.082],[111.548,12.521],[111.548,40.848]],"c":true},"ix":2},"nm":"Path 4","mn":"ADBE Vector Shape - Group","hd":false},{"ty":"fl","c":{"a":0,"k":[0.364705890417,0.858823537827,0.482352942228,1],"ix":4},"o":{"a":0,"k":100,"ix":5},"r":1,"bm":0,"nm":"Fill 1","mn":"ADBE Vector Graphic - Fill","hd":false},{"ty":"tr","p":{"a":0,"k":[-783.647,272.033],"ix":2},"a":{"a":0,"k":[0,0],"ix":1},"s":{"a":0,"k":[100,100],"ix":3},"r":{"a":0,"k":0,"ix":6},"o":{"a":0,"k":100,"ix":7},"sk":{"a":0,"k":0,"ix":4},"sa":{"a":0,"k":0,"ix":5},"nm":"Transform"}],"nm":"Group 4","np":5,"cix":2,"bm":0,"ix":4,"mn":"ADBE Vector Group","hd":false},{"ty":"gr","it":[{"ind":0,"ty":"sh","ix":1,"ks":{"a":0,"k":{"i":[[0,0],[0,0],[0,0],[0,0],[0,0],[0,0],[0,0]],"o":[[0,0],[0,0],[0,0],[0,0],[0,0],[0,0],[0,0]],"v":[[7.709,0.1],[8.128,-5.219],[3.407,-7.251],[-3.207,-5.737],[-8.128,2.132],[-8.128,7.251],[-2.41,7.251]],"c":true},"ix":2},"nm":"Path 1","mn":"ADBE Vector Shape - Group","hd":false},{"ty":"fl","c":{"a":0,"k":[0.364705890417,0.858823537827,0.482352942228,1],"ix":4},"o":{"a":0,"k":100,"ix":5},"r":1,"bm":0,"nm":"Fill 1","mn":"ADBE Vector Graphic - Fill","hd":false},{"ty":"tr","p":{"a":0,"k":[-1019.125,157.457],"ix":2},"a":{"a":0,"k":[0,0],"ix":1},"s":{"a":0,"k":[100,100],"ix":3},"r":{"a":0,"k":0,"ix":6},"o":{"a":0,"k":100,"ix":7},"sk":{"a":0,"k":0,"ix":4},"sa":{"a":0,"k":0,"ix":5},"nm":"Transform"}],"nm":"Group 5","np":2,"cix":2,"bm":0,"ix":5,"mn":"ADBE Vector Group","hd":false},{"ty":"gr","it":[{"ind":0,"ty":"sh","ix":1,"ks":{"a":0,"k":{"i":[[0,0],[0,0],[0,0],[0,0],[0,0],[0,0],[0,0],[0,0],[0,0],[0,0],[0,0],[0,0],[0,0],[0,0],[0,0]],"o":[[0,0],[0,0],[0,0],[0,0],[0,0],[0,0],[0,0],[0,0],[0,0],[0,0],[0,0],[0,0],[0,0],[0,0],[0,0]],"v":[[-2.958,0.717],[-2.44,4.701],[-8.377,5.936],[-9.194,14.403],[-2.042,14.403],[7.46,13.487],[12.361,7.67],[7.142,5.618],[4.293,2.351],[0.01,-4.602],[-2.042,-14.403],[-10.11,-12.769],[-12.361,-9.323],[-12.361,-5.419],[-8.496,-2.749]],"c":true},"ix":2},"nm":"Path 1","mn":"ADBE Vector Shape - Group","hd":false},{"ty":"fl","c":{"a":0,"k":[0.364705890417,0.858823537827,0.482352942228,1],"ix":4},"o":{"a":0,"k":100,"ix":5},"r":1,"bm":0,"nm":"Fill 1","mn":"ADBE Vector Graphic - Fill","hd":false},{"ty":"tr","p":{"a":0,"k":[-1001.604,153.572],"ix":2},"a":{"a":0,"k":[0,0],"ix":1},"s":{"a":0,"k":[100,100],"ix":3},"r":{"a":0,"k":0,"ix":6},"o":{"a":0,"k":100,"ix":7},"sk":{"a":0,"k":0,"ix":4},"sa":{"a":0,"k":0,"ix":5},"nm":"Transform"}],"nm":"Group 6","np":2,"cix":2,"bm":0,"ix":6,"mn":"ADBE Vector Group","hd":false},{"ty":"gr","it":[{"ind":0,"ty":"sh","ix":1,"ks":{"a":0,"k":{"i":[[0,0],[0,0],[0,0],[-0.518,0]],"o":[[0,0],[0,0],[0,0.398],[0.518,-0.02]],"v":[[2.301,3.715],[3.317,-2.719],[-3.317,-3.735],[-2.301,3.735]],"c":true},"ix":2},"nm":"Path 1","mn":"ADBE Vector Shape - Group","hd":false},{"ty":"fl","c":{"a":0,"k":[0.364705890417,0.858823537827,0.482352942228,1],"ix":4},"o":{"a":0,"k":100,"ix":5},"r":1,"bm":0,"nm":"Fill 1","mn":"ADBE Vector Graphic - Fill","hd":false},{"ty":"tr","p":{"a":0,"k":[-1340.622,156.71],"ix":2},"a":{"a":0,"k":[0,0],"ix":1},"s":{"a":0,"k":[100,100],"ix":3},"r":{"a":0,"k":0,"ix":6},"o":{"a":0,"k":100,"ix":7},"sk":{"a":0,"k":0,"ix":4},"sa":{"a":0,"k":0,"ix":5},"nm":"Transform"}],"nm":"Group 7","np":2,"cix":2,"bm":0,"ix":7,"mn":"ADBE Vector Group","hd":false},{"ty":"gr","it":[{"ind":0,"ty":"sh","ix":1,"ks":{"a":0,"k":{"i":[[0,0],[0,0],[0,0],[0,0],[0,0],[0,0],[0,0],[0,0],[0,0],[0,0],[0,0]],"o":[[0,0],[0,0],[0,0],[0,0],[0,0],[0,0],[0,0],[0,0],[0,0],[0,0],[0,0]],"v":[[-1.793,2.171],[3.088,2.171],[3.088,-0.359],[6.554,0.02],[6.096,-4.323],[0.498,-3.466],[0.02,-0.657],[-6.235,0.02],[-6.554,0.02],[-6.554,4.323],[-1.793,4.323]],"c":true},"ix":2},"nm":"Path 1","mn":"ADBE Vector Shape - Group","hd":false},{"ty":"fl","c":{"a":0,"k":[0.364705890417,0.858823537827,0.482352942228,1],"ix":4},"o":{"a":0,"k":100,"ix":5},"r":1,"bm":0,"nm":"Fill 1","mn":"ADBE Vector Graphic - Fill","hd":false},{"ty":"tr","p":{"a":0,"k":[-581.139,371.489],"ix":2},"a":{"a":0,"k":[0,0],"ix":1},"s":{"a":0,"k":[100,100],"ix":3},"r":{"a":0,"k":0,"ix":6},"o":{"a":0,"k":100,"ix":7},"sk":{"a":0,"k":0,"ix":4},"sa":{"a":0,"k":0,"ix":5},"nm":"Transform"}],"nm":"Group 8","np":2,"cix":2,"bm":0,"ix":8,"mn":"ADBE Vector Group","hd":false},{"ty":"gr","it":[{"ind":0,"ty":"sh","ix":1,"ks":{"a":0,"k":{"i":[[0,0],[0,0],[0,0],[0,0],[0,0],[0,0],[0,0],[0,0],[0,0],[0,0]],"o":[[0,0],[0,0],[0,0],[0,0],[0,0],[0,0],[0,0],[0,0],[0,0],[0,0]],"v":[[-0.378,1.345],[2.689,1.345],[2.689,-1.026],[4.901,-1.365],[4.901,-3.715],[0,-3.715],[-1.992,-1.365],[-4.901,1.345],[-4.901,3.715],[-0.378,3.257]],"c":true},"ix":2},"nm":"Path 1","mn":"ADBE Vector Shape - Group","hd":false},{"ty":"fl","c":{"a":0,"k":[0.364705890417,0.858823537827,0.482352942228,1],"ix":4},"o":{"a":0,"k":100,"ix":5},"r":1,"bm":0,"nm":"Fill 1","mn":"ADBE Vector Graphic - Fill","hd":false},{"ty":"tr","p":{"a":0,"k":[-595.124,370.164],"ix":2},"a":{"a":0,"k":[0,0],"ix":1},"s":{"a":0,"k":[100,100],"ix":3},"r":{"a":0,"k":0,"ix":6},"o":{"a":0,"k":100,"ix":7},"sk":{"a":0,"k":0,"ix":4},"sa":{"a":0,"k":0,"ix":5},"nm":"Transform"}],"nm":"Group 9","np":2,"cix":2,"bm":0,"ix":9,"mn":"ADBE Vector Group","hd":false},{"ty":"gr","it":[{"ind":0,"ty":"sh","ix":1,"ks":{"a":0,"k":{"i":[[0,0],[0,0],[0,0],[0,0]],"o":[[0,0],[0,0],[0,0],[0,0]],"v":[[-2.46,-1.365],[2.46,-1.365],[2.46,1.365],[-2.46,1.365]],"c":true},"ix":2},"nm":"Path 1","mn":"ADBE Vector Shape - Group","hd":false},{"ty":"fl","c":{"a":0,"k":[0.364705890417,0.858823537827,0.482352942228,1],"ix":4},"o":{"a":0,"k":100,"ix":5},"r":1,"bm":0,"nm":"Fill 1","mn":"ADBE Vector Graphic - Fill","hd":false},{"ty":"tr","p":{"a":0,"k":[-604.995,370.164],"ix":2},"a":{"a":0,"k":[0,0],"ix":1},"s":{"a":0,"k":[100,100],"ix":3},"r":{"a":0,"k":0,"ix":6},"o":{"a":0,"k":100,"ix":7},"sk":{"a":0,"k":0,"ix":4},"sa":{"a":0,"k":0,"ix":5},"nm":"Transform"}],"nm":"Group 10","np":2,"cix":2,"bm":0,"ix":10,"mn":"ADBE Vector Group","hd":false},{"ty":"gr","it":[{"ind":0,"ty":"sh","ix":1,"ks":{"a":0,"k":{"i":[[0,0],[0,0],[0,0],[0,0]],"o":[[0,0],[0,0],[0,0],[0,0]],"v":[[2.082,-1.614],[-2.082,-1.614],[-2.082,0.598],[1.145,1.614]],"c":true},"ix":2},"nm":"Path 1","mn":"ADBE Vector Shape - Group","hd":false},{"ty":"fl","c":{"a":0,"k":[0.364705890417,0.858823537827,0.482352942228,1],"ix":4},"o":{"a":0,"k":100,"ix":5},"r":1,"bm":0,"nm":"Fill 1","mn":"ADBE Vector Graphic - Fill","hd":false},{"ty":"tr","p":{"a":0,"k":[-586.07,367.186],"ix":2},"a":{"a":0,"k":[0,0],"ix":1},"s":{"a":0,"k":[100,100],"ix":3},"r":{"a":0,"k":0,"ix":6},"o":{"a":0,"k":100,"ix":7},"sk":{"a":0,"k":0,"ix":4},"sa":{"a":0,"k":0,"ix":5},"nm":"Transform"}],"nm":"Group 11","np":2,"cix":2,"bm":0,"ix":11,"mn":"ADBE Vector Group","hd":false},{"ty":"gr","it":[{"ind":0,"ty":"sh","ix":1,"ks":{"a":0,"k":{"i":[[0,0],[0,0],[0,0],[0,0],[0,0],[0,0],[0,0],[0,0],[0,0],[0,0],[0,0],[0,0]],"o":[[0,0],[0,0],[0,0],[0,0],[0,0],[0,0],[0,0],[0,0],[0,0],[0,0],[0,0],[0,0]],"v":[[0.936,-13.785],[-11.753,-15.439],[-11.753,-5.618],[-7.251,-0.299],[-10.737,5],[-15.837,10.937],[-15.837,21.754],[-8.885,28.507],[-2.53,18.327],[9.921,0.1],[15.837,-28.507],[8.287,-28.507]],"c":true},"ix":2},"nm":"Path 1","mn":"ADBE Vector Shape - Group","hd":false},{"ty":"fl","c":{"a":0,"k":[0.364705890417,0.858823537827,0.482352942228,1],"ix":4},"o":{"a":0,"k":100,"ix":5},"r":1,"bm":0,"nm":"Fill 1","mn":"ADBE Vector Graphic - Fill","hd":false},{"ty":"tr","p":{"a":0,"k":[-845.453,409.558],"ix":2},"a":{"a":0,"k":[0,0],"ix":1},"s":{"a":0,"k":[100,100],"ix":3},"r":{"a":0,"k":0,"ix":6},"o":{"a":0,"k":100,"ix":7},"sk":{"a":0,"k":0,"ix":4},"sa":{"a":0,"k":0,"ix":5},"nm":"Transform"}],"nm":"Group 12","np":2,"cix":2,"bm":0,"ix":12,"mn":"ADBE Vector Group","hd":false},{"ty":"gr","it":[{"ind":0,"ty":"sh","ix":1,"ks":{"a":0,"k":{"i":[[0,0],[0,0],[0,0],[0,0],[0,0]],"o":[[0,0],[0,0],[0,0],[0,0],[0,0]],"v":[[-6.454,0.329],[-3.885,7.261],[5.438,3.775],[6.454,-5.807],[-1.056,-7.261]],"c":true},"ix":2},"nm":"Path 1","mn":"ADBE Vector Shape - Group","hd":false},{"ty":"fl","c":{"a":0,"k":[0.364705890417,0.858823537827,0.482352942228,1],"ix":4},"o":{"a":0,"k":100,"ix":5},"r":1,"bm":0,"nm":"Fill 1","mn":"ADBE Vector Graphic - Fill","hd":false},{"ty":"tr","p":{"a":0,"k":[-728.954,314.505],"ix":2},"a":{"a":0,"k":[0,0],"ix":1},"s":{"a":0,"k":[100,100],"ix":3},"r":{"a":0,"k":0,"ix":6},"o":{"a":0,"k":100,"ix":7},"sk":{"a":0,"k":0,"ix":4},"sa":{"a":0,"k":0,"ix":5},"nm":"Transform"}],"nm":"Group 13","np":2,"cix":2,"bm":0,"ix":13,"mn":"ADBE Vector Group","hd":false},{"ty":"gr","it":[{"ind":0,"ty":"sh","ix":1,"ks":{"a":0,"k":{"i":[[0,0],[0,0],[0,0],[0,0],[0,0],[0,0],[0,0],[0,0],[0,0],[0,0],[0,0],[0,0],[0,0],[0,0],[0,0],[0,0],[0,0],[0,0],[0,0],[0,0]],"o":[[0,0],[0,0],[0,0],[0,0],[0,0],[0,0],[0,0],[0,0],[0,0],[0,0],[0,0],[0,0],[0,0],[0,0],[0,0],[0,0],[0,0],[0,0],[0,0],[0,0]],"v":[[-9.024,-8.078],[-15.897,-7.879],[-15.379,-15.03],[-21.913,-18.895],[-31.216,-9.592],[-24.981,-1.942],[-11.514,-0.01],[-3.924,3.974],[-3.725,7.68],[-8.646,7.68],[-8.447,15.23],[7.909,14.194],[13.845,7.879],[20.18,7.241],[20.18,18.895],[31.216,18.895],[31.216,14.194],[25.718,14.194],[24.662,-0.01],[-1.673,-11.963]],"c":true},"ix":2},"nm":"Path 1","mn":"ADBE Vector Shape - Group","hd":false},{"ty":"fl","c":{"a":0,"k":[0.364705890417,0.858823537827,0.482352942228,1],"ix":4},"o":{"a":0,"k":100,"ix":5},"r":1,"bm":0,"nm":"Fill 1","mn":"ADBE Vector Graphic - Fill","hd":false},{"ty":"tr","p":{"a":0,"k":[-530.141,356.837],"ix":2},"a":{"a":0,"k":[0,0],"ix":1},"s":{"a":0,"k":[100,100],"ix":3},"r":{"a":0,"k":0,"ix":6},"o":{"a":0,"k":100,"ix":7},"sk":{"a":0,"k":0,"ix":4},"sa":{"a":0,"k":0,"ix":5},"nm":"Transform"}],"nm":"Group 14","np":2,"cix":2,"bm":0,"ix":14,"mn":"ADBE Vector Group","hd":false},{"ty":"gr","it":[{"ind":0,"ty":"sh","ix":1,"ks":{"a":0,"k":{"i":[[0,0],[0,0],[0,0],[0,0],[0,0],[0,0],[0,0],[0,0],[0,0],[0,0],[0,0],[0,0],[0,0],[0,0],[0,0]],"o":[[0,0],[0,0],[0,0],[0,0],[0,0],[0,0],[0,0],[0,0],[0,0],[0,0],[0,0],[0,0],[0,0],[0,0],[0,0]],"v":[[28.019,-13.885],[23.577,-13.008],[23.437,-23.009],[15.309,-22.511],[14.273,-6.873],[7.122,-1.992],[-6.166,-0.139],[-27.402,15.001],[-31.047,17.949],[-31.047,23.009],[-19.891,21.296],[7.062,4.761],[14.692,-0.259],[22.84,-3.865],[31.047,-8.506]],"c":true},"ix":2},"nm":"Path 1","mn":"ADBE Vector Shape - Group","hd":false},{"ty":"fl","c":{"a":0,"k":[0.364705890417,0.858823537827,0.482352942228,1],"ix":4},"o":{"a":0,"k":100,"ix":5},"r":1,"bm":0,"nm":"Fill 1","mn":"ADBE Vector Graphic - Fill","hd":false},{"ty":"tr","p":{"a":0,"k":[-483.635,474.262],"ix":2},"a":{"a":0,"k":[0,0],"ix":1},"s":{"a":0,"k":[100,100],"ix":3},"r":{"a":0,"k":0,"ix":6},"o":{"a":0,"k":100,"ix":7},"sk":{"a":0,"k":0,"ix":4},"sa":{"a":0,"k":0,"ix":5},"nm":"Transform"}],"nm":"Group 15","np":2,"cix":2,"bm":0,"ix":15,"mn":"ADBE Vector Group","hd":false},{"ty":"gr","it":[{"ind":0,"ty":"sh","ix":1,"ks":{"a":0,"k":{"i":[[0,0],[0,0],[0,0],[0,0],[0,0]],"o":[[0,0],[0,0],[0,0],[0,0],[0,0]],"v":[[-9.702,4.98],[0.956,6.116],[9.542,1.375],[9.702,-5.1],[0.319,-6.116]],"c":true},"ix":2},"nm":"Path 1","mn":"ADBE Vector Shape - Group","hd":false},{"ty":"fl","c":{"a":0,"k":[0.364705890417,0.858823537827,0.482352942228,1],"ix":4},"o":{"a":0,"k":100,"ix":5},"r":1,"bm":0,"nm":"Fill 1","mn":"ADBE Vector Graphic - Fill","hd":false},{"ty":"tr","p":{"a":0,"k":[-548.289,484.86],"ix":2},"a":{"a":0,"k":[0,0],"ix":1},"s":{"a":0,"k":[100,100],"ix":3},"r":{"a":0,"k":0,"ix":6},"o":{"a":0,"k":100,"ix":7},"sk":{"a":0,"k":0,"ix":4},"sa":{"a":0,"k":0,"ix":5},"nm":"Transform"}],"nm":"Group 16","np":2,"cix":2,"bm":0,"ix":16,"mn":"ADBE Vector Group","hd":false},{"ty":"gr","it":[{"ind":0,"ty":"sh","ix":1,"ks":{"a":0,"k":{"i":[[0,0],[0,0],[0,0],[0,0],[0,0],[0,0],[0,0],[0,0],[0,0],[0,0],[0,0],[0,0],[0,0],[0,0],[0,0],[0,0],[0,0],[0,0],[0,0],[0,0],[0,0],[0,0],[0,0],[0,0],[0,0],[0,0],[0,0],[0,0],[0,0]],"o":[[0,0],[0,0],[0,0],[0,0],[0,0],[0,0],[0,0],[0,0],[0,0],[0,0],[0,0],[0,0],[0,0],[0,0],[0,0],[0,0],[0,0],[0,0],[0,0],[0,0],[0,0],[0,0],[0,0],[0,0],[0,0],[0,0],[0,0],[0,0],[0,0]],"v":[[64.684,-7.45],[53.667,-16.873],[52.851,-34.842],[45.579,-47.293],[39.045,-47.631],[36.396,-25.041],[23.885,-25.977],[20.399,-28.069],[19.981,-37.033],[26.595,-35.659],[32.153,-41.117],[20.3,-48.229],[6.335,-48.229],[-3.685,-34.025],[-7.769,-34.025],[-7.769,-38.527],[-19.742,-37.611],[-38.786,-15.957],[-48.847,-15.817],[-60.082,-8.068],[-60.919,25.439],[-67.652,31.973],[-67.652,37.91],[-34.922,26.674],[-8.427,25.619],[1.375,47.213],[31.495,48.229],[60.52,20.957],[67.652,4.642]],"c":true},"ix":2},"nm":"Path 1","mn":"ADBE Vector Shape - Group","hd":false},{"ty":"fl","c":{"a":0,"k":[0.364705890417,0.858823537827,0.482352942228,1],"ix":4},"o":{"a":0,"k":100,"ix":5},"r":1,"bm":0,"nm":"Fill 1","mn":"ADBE Vector Graphic - Fill","hd":false},{"ty":"tr","p":{"a":0,"k":[-563.31,426.013],"ix":2},"a":{"a":0,"k":[0,0],"ix":1},"s":{"a":0,"k":[100,100],"ix":3},"r":{"a":0,"k":0,"ix":6},"o":{"a":0,"k":100,"ix":7},"sk":{"a":0,"k":0,"ix":4},"sa":{"a":0,"k":0,"ix":5},"nm":"Transform"}],"nm":"Group 17","np":2,"cix":2,"bm":0,"ix":17,"mn":"ADBE Vector Group","hd":false},{"ty":"gr","it":[{"ind":0,"ty":"sh","ix":1,"ks":{"a":0,"k":{"i":[[0,0],[0,0],[0,0],[0,0],[0,0],[0,0],[0,0],[0,0],[0,0],[0,0]],"o":[[0,0],[0,0],[0,0],[0,0],[0,0],[0,0],[0,0],[0,0],[0,0],[0,0]],"v":[[6.594,-10.777],[-4.223,-6.574],[-4.064,-4.144],[-6.753,-4.144],[-6.753,10.777],[-1.235,10.777],[-2.052,1.255],[2.251,2.809],[2.251,9.542],[6.753,9.144]],"c":true},"ix":2},"nm":"Path 1","mn":"ADBE Vector Shape - Group","hd":false},{"ty":"fl","c":{"a":0,"k":[0.364705890417,0.858823537827,0.482352942228,1],"ix":4},"o":{"a":0,"k":100,"ix":5},"r":1,"bm":0,"nm":"Fill 1","mn":"ADBE Vector Graphic - Fill","hd":false},{"ty":"tr","p":{"a":0,"k":[-593.271,350.891],"ix":2},"a":{"a":0,"k":[0,0],"ix":1},"s":{"a":0,"k":[100,100],"ix":3},"r":{"a":0,"k":0,"ix":6},"o":{"a":0,"k":100,"ix":7},"sk":{"a":0,"k":0,"ix":4},"sa":{"a":0,"k":0,"ix":5},"nm":"Transform"}],"nm":"Group 18","np":2,"cix":2,"bm":0,"ix":18,"mn":"ADBE Vector Group","hd":false},{"ty":"gr","it":[{"ind":0,"ty":"sh","ix":1,"ks":{"a":0,"k":{"i":[[0,0],[0,0],[0,0],[0,0],[0,0],[0,0],[0,0],[0,0],[0,0],[0,0],[0,0],[0,0],[0,0],[0,0]],"o":[[0,0],[0,0],[0,0],[0,0],[0,0],[0,0],[0,0],[0,0],[0,0],[0,0],[0,0],[0,0],[0,0],[0,0]],"v":[[14.483,8.516],[17.013,6.843],[17.013,-13.337],[14.483,-14.393],[13.267,-20.688],[9.582,-20.688],[7.211,-14.313],[4.383,-11.783],[-17.013,-0.189],[-17.013,11.285],[-9.881,20.688],[8.148,20.688],[10.439,14.871],[14.483,11.186]],"c":true},"ix":2},"nm":"Path 1","mn":"ADBE Vector Shape - Group","hd":false},{"ty":"fl","c":{"a":0,"k":[0.364705890417,0.858823537827,0.482352942228,1],"ix":4},"o":{"a":0,"k":100,"ix":5},"r":1,"bm":0,"nm":"Fill 1","mn":"ADBE Vector Graphic - Fill","hd":false},{"ty":"tr","p":{"a":0,"k":[-617.037,333.271],"ix":2},"a":{"a":0,"k":[0,0],"ix":1},"s":{"a":0,"k":[100,100],"ix":3},"r":{"a":0,"k":0,"ix":6},"o":{"a":0,"k":100,"ix":7},"sk":{"a":0,"k":0,"ix":4},"sa":{"a":0,"k":0,"ix":5},"nm":"Transform"}],"nm":"Group 19","np":2,"cix":2,"bm":0,"ix":19,"mn":"ADBE Vector Group","hd":false},{"ty":"gr","it":[{"ind":0,"ty":"sh","ix":1,"ks":{"a":0,"k":{"i":[[0,0],[0,0],[0,0],[0,0],[0,0],[0,0],[0,0],[0,0],[0,0],[0,0],[0,0],[0,0],[0,0],[0,0],[0,0],[0,0],[0,0]],"o":[[0,0],[0,0],[0,0],[0,0],[0,0],[0,0],[0,0],[0,0],[0,0],[0,0],[0,0],[0,0],[0,0],[0,0],[0,0],[0,0],[0,0]],"v":[[21.266,17.471],[6.126,17.889],[5.508,9.702],[7.958,10.737],[13.895,10.12],[13.277,2.57],[-3.058,2.769],[-7.56,-3.148],[-7.321,-6.255],[-28.398,-25.26],[-33.517,-21.156],[-3.476,15.638],[0.807,17.072],[0.807,19.104],[-4.911,19.104],[-3.476,23.626],[33.517,25.26]],"c":true},"ix":2},"nm":"Path 1","mn":"ADBE Vector Shape - Group","hd":false},{"ty":"fl","c":{"a":0,"k":[0.364705890417,0.858823537827,0.482352942228,1],"ix":4},"o":{"a":0,"k":100,"ix":5},"r":1,"bm":0,"nm":"Fill 1","mn":"ADBE Vector Graphic - Fill","hd":false},{"ty":"tr","p":{"a":0,"k":[-647.506,343.54],"ix":2},"a":{"a":0,"k":[0,0],"ix":1},"s":{"a":0,"k":[100,100],"ix":3},"r":{"a":0,"k":0,"ix":6},"o":{"a":0,"k":100,"ix":7},"sk":{"a":0,"k":0,"ix":4},"sa":{"a":0,"k":0,"ix":5},"nm":"Transform"}],"nm":"Group 20","np":2,"cix":2,"bm":0,"ix":20,"mn":"ADBE Vector Group","hd":false},{"ty":"tr","p":{"a":0,"k":[-647.506,343.54],"ix":2},"a":{"a":0,"k":[-647.506,343.54],"ix":1},"s":{"a":0,"k":[100,100],"ix":3},"r":{"a":0,"k":0,"ix":6},"o":{"a":0,"k":100,"ix":7},"sk":{"a":0,"k":0,"ix":4},"sa":{"a":0,"k":0,"ix":5},"nm":"Transform"}],"nm":"Group 1","np":20,"cix":2,"bm":0,"ix":1,"mn":"ADBE Vector Group","hd":false},{"ty":"tr","p":{"a":0,"k":[-647.506,343.54],"ix":2},"a":{"a":0,"k":[-647.506,343.54],"ix":1},"s":{"a":0,"k":[100,100],"ix":3},"r":{"a":0,"k":0,"ix":6},"o":{"a":0,"k":100,"ix":7},"sk":{"a":0,"k":0,"ix":4},"sa":{"a":0,"k":0,"ix":5},"nm":"Transform"}],"nm":"Group 1","np":1,"cix":2,"bm":0,"ix":1,"mn":"ADBE Vector Group","hd":false},{"ty":"gr","it":[{"ty":"gr","it":[{"ty":"gr","it":[{"ind":0,"ty":"sh","ix":1,"ks":{"a":0,"k":{"i":[[0,0],[-0.438,0],[0,0],[0,0],[0,0]],"o":[[0,0],[0.438,0],[0,0],[0,0],[0,0]],"v":[[-20.25,-182.139],[-14.433,-183.055],[-14.433,-177.696],[-26.545,-176.919],[-28.856,-179.688]],"c":true},"ix":2},"nm":"Path 1","mn":"ADBE Vector Shape - Group","hd":false},{"ind":1,"ty":"sh","ix":2,"ks":{"a":0,"k":{"i":[[0,0],[0,0],[0,0],[0,0],[0,0],[0,0],[0,0],[0,0]],"o":[[0,0],[0,0],[0,0],[0,0],[0,0],[0,0],[0,0],[0,0]],"v":[[-28.836,-194.091],[-28.836,-194.55],[-23.457,-194.55],[-22.999,-196.382],[-14.214,-196.382],[-14.214,-192.557],[-16.724,-189.191],[-28.836,-189.191]],"c":true},"ix":2},"nm":"Path 2","mn":"ADBE Vector Shape - Group","hd":false},{"ind":2,"ty":"sh","ix":3,"ks":{"a":0,"k":{"i":[[0,0],[0,0],[0,0],[0,0],[0,0]],"o":[[0,0],[0,0],[0,0],[0,0],[0,0]],"v":[[0.289,-156.998],[6.106,-155.624],[4.094,-147.795],[-2.181,-145.803],[-6.166,-153.93]],"c":true},"ix":2},"nm":"Path 3","mn":"ADBE Vector Shape - Group","hd":false},{"ind":3,"ty":"sh","ix":4,"ks":{"a":0,"k":{"i":[[0,0],[0,0],[0,0],[0,0],[0,0]],"o":[[0,0],[0,0],[0,0],[0,0],[0,0]],"v":[[7.799,-122.355],[13.477,-128.491],[21.604,-128.491],[11.186,-113.929],[6.883,-116.24]],"c":true},"ix":2},"nm":"Path 4","mn":"ADBE Vector Shape - Group","hd":false},{"ind":4,"ty":"sh","ix":5,"ks":{"a":0,"k":{"i":[[0,0],[0,0],[0,0],[0,0],[0,0],[0,0],[0,0],[0,0]],"o":[[0,0],[0,0],[0,0],[0,0],[0,0],[0,0],[0,0],[0,0]],"v":[[9.174,-135.523],[16.226,-138.432],[25.887,-138.432],[25.887,-135.523],[28.019,-135.523],[28.019,-130.463],[13.317,-130.463],[7.799,-131.997]],"c":true},"ix":2},"nm":"Path 5","mn":"ADBE Vector Shape - Group","hd":false},{"ind":5,"ty":"sh","ix":6,"ks":{"a":0,"k":{"i":[[0,0],[0,0],[0,0]],"o":[[0,0],[0,0],[0,0]],"v":[[30.629,-136.3],[35.689,-131.698],[30.629,-130.463]],"c":true},"ix":2},"nm":"Path 6","mn":"ADBE Vector Shape - Group","hd":false},{"ind":6,"ty":"sh","ix":7,"ks":{"a":0,"k":{"i":[[0,0],[0,0],[0,0],[0,0],[0,0],[0,0]],"o":[[0,0],[0,0],[0,0],[0,0],[0,0],[0,0]],"v":[[36.784,-123.112],[37.402,-123.112],[46.745,-120.343],[46.745,-115.582],[38.916,-115.582],[36.784,-118.67]],"c":true},"ix":2},"nm":"Path 7","mn":"ADBE Vector Shape - Group","hd":false},{"ind":7,"ty":"sh","ix":8,"ks":{"a":0,"k":{"i":[[0,0],[0,0],[0,0],[0,0]],"o":[[0,0],[0,0],[0,0],[0,0]],"v":[[41.745,-129.248],[45.51,-126.898],[42.502,-124.407],[39.533,-126.898]],"c":true},"ix":2},"nm":"Path 8","mn":"ADBE Vector Shape - Group","hd":false},{"ind":8,"ty":"sh","ix":9,"ks":{"a":0,"k":{"i":[[0,0],[0,0],[0,0],[0,0.777],[0,0],[0,0]],"o":[[0,0],[0,0],[0,0],[0,0],[0,0],[0,0]],"v":[[34.792,-123.571],[31.107,-121.2],[26.525,-120.363],[26.525,-128.491],[34.812,-128.491],[34.792,-123.571]],"c":true},"ix":2},"nm":"Path 9","mn":"ADBE Vector Shape - Group","hd":false},{"ind":9,"ty":"sh","ix":10,"ks":{"a":0,"k":{"i":[[0,0],[0,0],[0,0],[0,0],[0,0],[0,0],[0,0]],"o":[[0,0],[0,0],[0,0],[0,0],[0,0],[0,0],[0,0]],"v":[[32.94,-113.909],[29.414,-110.383],[21.585,-110.383],[22.82,-115.742],[26.505,-116.06],[27.282,-117.893],[32.94,-118.67]],"c":true},"ix":2},"nm":"Path 10","mn":"ADBE Vector Shape - Group","hd":false},{"ind":10,"ty":"sh","ix":11,"ks":{"a":0,"k":{"i":[[0,0],[0,0],[0,0],[0,0],[0,0],[0,0],[0,0],[0,0],[0,0],[0,0],[0,0],[0,0],[0,0],[0,0],[0,0],[0,0],[0,0],[0,0],[0,0],[0,0],[0,0],[0,0],[0,0],[0,0],[0,0],[0,0],[0,0],[0,0],[0,0],[0,0],[0,0],[0,0],[0,0],[0,0],[0,0],[0,0],[0,0],[0,0],[0,0],[0,0],[0,0],[0,0],[0,0],[0,0],[0,0],[0,0],[0,0],[0,0],[0,0],[0,0],[0,0],[0,0],[0,0],[0,0],[0,0],[0,0],[0,0],[-0.02,-0.1],[0,0],[0,0],[0,0],[0,0],[0,0],[0,0],[0,0],[0,0],[0,0],[0,0],[0,0],[0,0],[0,0],[0,0],[0,0],[0,0],[0,0],[0,0],[0,0],[0,0],[0,0],[0,0],[0,0],[0,0],[0,0],[0,0],[0,0],[0,0],[0,0],[0,0],[0,0],[0,0],[0,0],[0,0],[0,0],[0,0],[0,0],[0,0],[0,0],[0,0],[0,0],[0,0],[0,0],[0,0],[0,0],[0,0],[0,0],[0,0],[0,0],[0,0],[0,0],[0,0],[0,0],[0,0],[0,0],[0,0],[0,0],[0,0],[0,0],[0.598,0],[0,0],[0,0],[0,0],[0,0],[0,0],[0,0],[0,0],[0,0],[0,0],[0,0],[0,0],[0,0],[0,0],[0,0],[0,0],[0,0],[0,0],[0,0],[0,0],[0,0],[0,0],[0,0],[0,0],[0,0],[0,0],[0,0],[0,0],[0,0],[0,0],[0,0],[0,0],[0,0],[0,0],[0,0],[0,0],[0,0],[0,0],[0,0],[0,0],[0,0],[0,0],[0,0],[0,0],[0,0],[0,0],[0,0],[0,0],[0,0],[0,0],[0,0],[0,0],[0,0],[0,0],[0,0],[0,0],[0,0],[0,0],[0,0],[0,0],[0,0],[0,0],[0,0],[0,0],[0,0],[0,0],[0,0],[0,0],[-0.817,0],[0,0],[0,0],[0,0],[0,0],[0,0],[0,0],[0,0],[0,0],[0,0],[0,0],[0,0],[0,0],[0,0],[0,0],[0,0],[0,0],[0,0],[0,0],[0,0],[0,0],[0,0],[0,0],[0,0],[0,0],[0,0],[0,0],[0,0],[0,0],[0,0],[0,0],[0,0],[0,0]],"o":[[0,0],[0,0],[0,0],[0,0],[0,0],[0,0],[0,0],[0,0],[0,0],[0,0],[0,0],[0,0],[0,0],[0,0],[0,0],[0,0],[0,0],[0,0],[0,0],[0,0],[0,0],[0,0],[0,0],[0,0],[0,0],[0,0],[0,0],[0,0],[0,0],[0,0],[0,0],[0,0],[0,0],[0,0],[0,0],[0,0],[0,0],[0,0],[0,0],[0,0],[0,0],[0,0],[0,0],[0,0],[0,0],[0,0],[0,0],[0,0],[0,0],[0,0],[0,0],[0,0],[0,0],[0,0],[0,0],[0,0],[0,0],[0,0],[0,0],[0,0],[0,0],[0,0],[0,0],[0,0],[0,0],[0,0],[0,0],[0,0],[0,0],[0,0],[0,0],[0,0],[0,0],[0,0],[0,0],[0,0],[0,0],[0,0],[0,0],[0,0],[0,0],[0,0],[0,0],[0,0],[0,0],[0,0],[0,0],[0,0],[0,0],[0,0],[0,0],[0,0],[0,0],[0,0],[0,0],[0,0],[0,0],[0,0],[0,0],[0,0],[0,0],[0,0],[0,0],[0,0],[0,0],[0,0],[0,0],[0,0],[0,0],[0,0],[0,0],[0,0],[0,0],[0,0],[0,0],[0,0],[0,0],[-0.598,0],[0,0],[0,0],[0,0],[0,0],[0,0],[0,0],[0,0],[0,0],[0,0],[0,0],[0,0],[0,0],[0,0],[0,0],[0,0],[0,0],[0,0],[0,0],[0,0],[0,0],[0,0],[0,0],[0,0],[0,0],[0,0],[0,0],[0,0],[0,0],[0,0],[0,0],[0,0],[0,0],[0,0],[0,0],[0,0],[0,0],[0,0],[0,0],[0,0],[0,0],[0,0],[0,0],[0,0],[0,0],[0,0],[0,0],[0,0],[0,0],[0,0],[0,0],[0,0],[0,0],[0,0],[0,0],[0,0],[0,0],[0,0],[0,0],[0,0],[0,0],[0,0],[0,0],[0,0],[0,0],[0,0],[0,0],[0,0],[0.817,0],[0,0],[0,0],[0,0],[0,0],[0,0],[0,0],[0,0],[0,0],[0,0],[0,0],[0,0],[0,0],[0,0],[0,0],[0,0],[0,0],[0,0],[0,0],[0,0],[0,0],[0,0],[0,0],[0,0],[0,0],[0,0],[0,0],[0,0],[0,0],[0,0],[0,0],[0,0],[0,0]],"v":[[144.02,37.173],[122.365,36.954],[105.193,30.439],[104.377,18.188],[98.639,8.148],[83.121,7.929],[74.116,-6.156],[66.148,-10.04],[65.73,-5.757],[51.207,-4.901],[45.888,-12.291],[30.768,-15.359],[18.337,-0.956],[-1.285,-4.263],[-2.719,-26.376],[-17.023,-28.826],[-11.285,-39.663],[-12.939,-45.898],[-31.744,-33.328],[-43.577,-34.762],[-47.821,-44.006],[-45.231,-53.548],[-38.697,-65.58],[-23.676,-73.19],[5.349,-73.19],[5.269,-64.345],[15.688,-59.484],[14.851,-74.605],[22.361,-82.155],[37.541,-92.115],[38.577,-99.128],[53.697,-114.865],[69.774,-123.77],[68.359,-124.945],[79.256,-135.205],[83.24,-134.149],[85.073,-131.858],[89.217,-136.44],[90.233,-136.878],[85.691,-137.515],[81.109,-139.049],[81.109,-143.492],[83.559,-145.484],[88.938,-145.484],[91.408,-144.408],[93.54,-140.125],[96.149,-140.524],[96.149,-140.902],[96.906,-140.643],[104.436,-141.818],[105.512,-145.504],[109.795,-144.428],[109.795,-140.444],[105.811,-137.695],[105.811,-137.695],[106.389,-133.312],[120.055,-129.109],[120.094,-128.949],[123.222,-129.228],[123.441,-135.145],[112.564,-140.025],[111.947,-142.874],[120.931,-145.942],[121.33,-154.528],[111.947,-160.245],[111.329,-174.748],[98.46,-168.413],[93.759,-168.413],[94.994,-179.449],[77.463,-183.593],[70.212,-178.115],[70.212,-161.401],[57.184,-157.257],[51.964,-146.38],[46.307,-145.464],[46.307,-159.409],[34.055,-161.102],[27.919,-165.086],[25.449,-174.13],[47.382,-186.96],[58.12,-190.227],[59.196,-183.015],[65.172,-183.334],[65.63,-186.96],[71.885,-187.856],[71.985,-189.111],[69.296,-190.227],[68.678,-194.052],[76.368,-194.689],[81.009,-199.53],[81.268,-199.888],[81.328,-199.868],[82.742,-201.323],[98.898,-203.375],[106.03,-197.299],[87.304,-187.338],[111.13,-181.72],[114.218,-189.689],[124.636,-189.689],[128.322,-196.641],[120.951,-198.474],[120.951,-207.259],[97.863,-217.479],[81.926,-215.646],[72.921,-210.945],[73.539,-199.49],[64.136,-200.924],[62.682,-207.259],[71.686,-215.447],[55.331,-216.284],[50.63,-214.849],[48.578,-209.331],[54.713,-208.295],[53.478,-202.159],[43.059,-201.542],[41.426,-197.458],[26.306,-197.06],[25.29,-205.646],[37.143,-205.845],[46.147,-214.63],[41.227,-217.08],[34.693,-210.745],[23.836,-211.363],[17.301,-220.367],[3.397,-220.367],[-11.126,-209.53],[2.161,-209.53],[3.377,-205.646],[-0.09,-202.379],[14.632,-201.96],[16.883,-196.641],[0.309,-197.259],[-0.508,-201.343],[-10.927,-203.594],[-16.445,-206.662],[-40.968,-206.462],[-48.538,-199.112],[-53.638,-199.53],[-59.355,-202.797],[-76.328,-207.897],[-107.405,-207.897],[-125.354,-195.625],[-137.406,-193.773],[-142.924,-189.49],[-134.338,-188.215],[-134.338,-184.788],[-152.725,-184.788],[-159.897,-179.688],[-150.713,-171.919],[-125.573,-171.72],[-122.106,-175.405],[-101.05,-175.405],[-93.5,-168.652],[-93.898,-158.233],[-87.563,-152.317],[-92.882,-148.552],[-91.647,-134.746],[-110.652,-111.658],[-110.652,-90.004],[-100.432,-85.083],[-100.432,-65.62],[-90.631,-48.906],[-82.663,-47.671],[-81.647,-53.409],[-91.049,-67.931],[-92.882,-82.035],[-87.364,-82.035],[-85.033,-67.513],[-71.427,-47.691],[-74.953,-41.277],[-66.307,-28.069],[-44.852,-22.75],[-44.852,-26.216],[-36.266,-24.981],[-37.083,-18.845],[-30.35,-17.61],[-19.931,-14.761],[-5.209,2.012],[13.576,3.426],[15.409,18.766],[2.54,27.77],[1.922,41.496],[0.09,49.863],[18.696,73.17],[20.13,81.139],[27.7,82.971],[42.82,93.789],[42.82,135.882],[47.92,137.316],[44.434,156.739],[53.02,168.174],[51.426,187.438],[62.761,207.359],[77.324,220.089],[91.966,220.367],[93.4,215.666],[82.643,206.602],[83.26,202.1],[85.193,196.601],[85.611,190.964],[78.34,190.765],[74.674,186.183],[80.71,180.366],[81.527,175.943],[74.794,174.011],[75.192,169.947],[84.794,168.473],[99.416,161.441],[104.317,152.436],[119.656,132.834],[116.17,117.475],[120.871,109.327],[134.976,109.745],[144.478,102.235],[147.546,72.652],[158.064,59.265],[159.897,50.659],[150.295,47.611]],"c":true},"ix":2},"nm":"Path 11","mn":"ADBE Vector Shape - Group","hd":false},{"ty":"fl","c":{"a":0,"k":[0.364705890417,0.858823537827,0.482352942228,1],"ix":4},"o":{"a":0,"k":100,"ix":5},"r":1,"bm":0,"nm":"Fill 1","mn":"ADBE Vector Graphic - Fill","hd":false},{"ty":"tr","p":{"a":0,"k":[-306.979,310.77],"ix":2},"a":{"a":0,"k":[0,0],"ix":1},"s":{"a":0,"k":[100,100],"ix":3},"r":{"a":0,"k":0,"ix":6},"o":{"a":0,"k":100,"ix":7},"sk":{"a":0,"k":0,"ix":4},"sa":{"a":0,"k":0,"ix":5},"nm":"Transform"}],"nm":"Group 1","np":12,"cix":2,"bm":0,"ix":1,"mn":"ADBE Vector Group","hd":false},{"ty":"gr","it":[{"ind":0,"ty":"sh","ix":1,"ks":{"a":0,"k":{"i":[[0,0],[0,0],[0,0],[0,0],[0,0]],"o":[[0,0],[0,0],[0,0],[0,0],[0,0]],"v":[[-2.829,3.207],[2.291,2.769],[2.829,-0.797],[-0.239,-3.207],[-2.55,-0.359]],"c":true},"ix":2},"nm":"Path 1","mn":"ADBE Vector Shape - Group","hd":false},{"ty":"fl","c":{"a":0,"k":[0.364705890417,0.858823537827,0.482352942228,1],"ix":4},"o":{"a":0,"k":100,"ix":5},"r":1,"bm":0,"nm":"Fill 1","mn":"ADBE Vector Graphic - Fill","hd":false},{"ty":"tr","p":{"a":0,"k":[-227.344,187.079],"ix":2},"a":{"a":0,"k":[0,0],"ix":1},"s":{"a":0,"k":[100,100],"ix":3},"r":{"a":0,"k":0,"ix":6},"o":{"a":0,"k":100,"ix":7},"sk":{"a":0,"k":0,"ix":4},"sa":{"a":0,"k":0,"ix":5},"nm":"Transform"}],"nm":"Group 2","np":2,"cix":2,"bm":0,"ix":2,"mn":"ADBE Vector Group","hd":false},{"ty":"gr","it":[{"ind":0,"ty":"sh","ix":1,"ks":{"a":0,"k":{"i":[[0,0],[0,0],[0,0],[0,0],[-0.139,-1.016],[0,0],[0,0],[0,0],[0,0],[0,0],[0,0],[0,0]],"o":[[0,0],[0,0],[0,0],[0,0],[0,0],[0,0],[0,0],[0,0],[0,0],[0,0],[0,0],[0,0]],"v":[[-0.199,-0.807],[-7.251,-0.807],[-7.251,2.819],[-5.578,2.819],[-5.339,4.612],[-1.016,4.253],[1.673,2.58],[2.391,-0.807],[5.877,-1.106],[7.251,-3.954],[4.044,-4.612],[1.235,-4.552]],"c":true},"ix":2},"nm":"Path 1","mn":"ADBE Vector Shape - Group","hd":false},{"ty":"fl","c":{"a":0,"k":[0.364705890417,0.858823537827,0.482352942228,1],"ix":4},"o":{"a":0,"k":100,"ix":5},"r":1,"bm":0,"nm":"Fill 1","mn":"ADBE Vector Graphic - Fill","hd":false},{"ty":"tr","p":{"a":0,"k":[-212.981,184.679],"ix":2},"a":{"a":0,"k":[0,0],"ix":1},"s":{"a":0,"k":[100,100],"ix":3},"r":{"a":0,"k":0,"ix":6},"o":{"a":0,"k":100,"ix":7},"sk":{"a":0,"k":0,"ix":4},"sa":{"a":0,"k":0,"ix":5},"nm":"Transform"}],"nm":"Group 3","np":2,"cix":2,"bm":0,"ix":3,"mn":"ADBE Vector Group","hd":false},{"ty":"gr","it":[{"ind":0,"ty":"sh","ix":1,"ks":{"a":0,"k":{"i":[[0,0],[0,0],[0,0],[0,0],[0,0],[0,0],[0,0],[0,0],[0,0],[0,0],[0,0],[0,0],[0,0],[0,0],[0,0],[0,0],[0,0],[0,0],[0,0],[0,0]],"o":[[0,0],[0,0],[0,0],[0,0],[0,0],[0,0],[0,0],[0,0],[0,0],[0,0],[0,0],[0,0],[0,0],[0,0],[0,0],[0,0],[0,0],[0,0],[0,0],[0,0]],"v":[[-44.235,-60.212],[-47.004,-57.562],[-53.419,-58.08],[-54.654,-60.012],[-64.773,-60.729],[-64.056,-63.997],[-58.717,-68.598],[-58.717,-72.463],[-68.957,-79.933],[-69.375,-89.436],[-67.303,-94.137],[-59.036,-94.854],[-51.984,-91.906],[-51.665,-86.985],[-61.666,-87.543],[-62.184,-82.981],[-49.613,-74.595],[-49.613,-68.459],[-44.195,-64.475],[-44.195,-60.211]],"c":true},"ix":2},"nm":"Path 1","mn":"ADBE Vector Shape - Group","hd":false},{"ind":1,"ty":"sh","ix":2,"ks":{"a":0,"k":{"i":[[0,0],[0,0],[0,0],[0,0],[0,0],[0,0],[0,0],[0,0],[0,0],[0,0],[0,0],[0,0]],"o":[[0,0],[0,0],[0,0],[0,0],[0,0],[0,0],[0,0],[0,0],[0,0],[0,0],[0,0],[0,0]],"v":[[-105.313,-67.981],[-121.21,-68.638],[-125.971,-67.981],[-125.971,-78.838],[-122.385,-82.842],[-118.561,-84.037],[-110.094,-85.013],[-108.261,-87.902],[-104.795,-86.189],[-104.337,-76.288],[-95.074,-72.503],[-94.257,-67.981]],"c":true},"ix":2},"nm":"Path 2","mn":"ADBE Vector Shape - Group","hd":false},{"ind":2,"ty":"sh","ix":3,"ks":{"a":0,"k":{"i":[[0,0],[0,0],[0,0],[0,0],[0,0],[0,0],[0,0],[0,0],[0,0],[0,0],[0,0],[0,0]],"o":[[0,0],[0,0],[0,0],[0,0],[0,0],[0,0],[0,0],[0,0],[0,0],[0,0],[0,0],[0,0]],"v":[[-142.805,-153.203],[-154.976,-145.753],[-154.976,-140.852],[-148.064,-137.625],[-147.625,-131.031],[-157.347,-116.548],[-174.22,-116.708],[-175.276,-120.234],[-164.718,-125.593],[-164.638,-145.593],[-146.709,-158.084],[-142.805,-158.084]],"c":true},"ix":2},"nm":"Path 3","mn":"ADBE Vector Shape - Group","hd":false},{"ind":3,"ty":"sh","ix":4,"ks":{"a":0,"k":{"i":[[0,0],[0,0],[0,0],[0,0],[0,0],[0,0],[0,0],[0,0],[0,0],[0,0],[0,0],[0,0],[0,0],[0,0],[0,0],[0,0],[0,0],[0,0],[0,0],[0,0],[0,0],[0,0],[0,0],[0,0],[0,0],[0,0],[0,0],[0,0],[0,0],[0,0],[0,0],[0,0],[0,0],[0,0],[0,0],[0,0],[0,0],[0,0],[0,0],[0,0],[0,0],[0,0],[0,0],[0,0],[0,0],[0,0],[0,0],[0,0],[0,0],[0,0],[0,0],[0,0],[0,0],[0,0],[0,0],[0,0],[0,0],[0,0],[0,0],[0,0],[0,0],[0,0],[0,0],[0,0],[0,0],[0,0],[0,0],[0,0],[0,0],[0,0],[0,0],[0,0],[0,0],[0,0],[0,0],[0,0],[0,0],[0,0],[0,0],[0,0],[0,0],[0,0],[0,0],[0,0],[0,0],[0,0],[0,0],[0,0],[0,0],[0,0],[0,0],[0,0],[0,0],[0,0],[0,0],[0,0],[0,0],[0,0],[0,0],[0,0],[0,0],[0,0],[0,0],[0,0],[0,0],[0,0],[0,0],[0,0],[0,0],[0,0],[0,0],[0,0],[0,0],[0,0],[0,0],[0,0],[0,0],[0,0],[0,0],[0,0],[0,0],[0,0],[0,0],[0,0],[0,0],[0,0],[0,0],[0,0],[0,0],[0,0],[0,0],[0,0],[0,0],[0,0],[0,0],[0,0],[0,0],[0,0],[0,0],[0,0],[0,0],[0,0],[0,0],[0,0],[0,0],[0,0],[0,0],[0,0],[0,0],[0,0],[0,0],[0,0],[0,0],[0,0],[0,0],[0,0],[0,0],[0,0],[0,0],[0,0],[0,0],[0,0],[0,0],[0,0],[0,0],[0,0],[0,0],[0,0],[0,0],[0,0],[0,0],[0,0],[0,0],[0,0],[0,0],[0,0],[0,0],[0,0],[0,0],[0,0],[0,0],[0,0],[0,0],[0,0],[0,0],[0,0],[0,0],[0,0],[0,0],[0,0],[0,0],[0,0],[0,0],[0,0],[0,0],[0,0],[0,0],[0,0],[0,0],[0,0.637],[0,0],[0,0],[0,0],[0,0],[0,0],[0,0],[0,0],[0,0],[0,0],[0,0],[0,0],[0,0],[0,0],[0,0],[0,0],[0,0],[0,0],[0,0]],"o":[[0,0],[0,0],[0,0],[0,0],[0,0],[0,0],[0,0],[0,0],[0,0],[0,0],[0,0],[0,0],[0,0],[0,0],[0,0],[0,0],[0,0],[0,0],[0,0],[0,0],[0,0],[0,0],[0,0],[0,0],[0,0],[0,0],[0,0],[0,0],[0,0],[0,0],[0,0],[0,0],[0,0],[0,0],[0,0],[0,0],[0,0],[0,0],[0,0],[0,0],[0,0],[0,0],[0,0],[0,0],[0,0],[0,0],[0,0],[0,0],[0,0],[0,0],[0,0],[0,0],[0,0],[0,0],[0,0],[0,0],[0,0],[0,0],[0,0],[0,0],[0,0],[0,0],[0,0],[0,0],[0,0],[0,0],[0,0],[0,0],[0,0],[0,0],[0,0],[0,0],[0,0],[0,0],[0,0],[0,0],[0,0],[0,0],[0,0],[0,0],[0,0],[0,0],[0,0],[0,0],[0,0],[0,0],[0,0],[0,0],[0,0],[0,0],[0,0],[0,0],[0,0],[0,0],[0,0],[0,0],[0,0],[0,0],[0,0],[0,0],[0,0],[0,0],[0,0],[0,0],[0,0],[0,0],[0,0],[0,0],[0,0],[0,0],[0,0],[0,0],[0,0],[0,0],[0,0],[0,0],[0,0],[0,0],[0,0],[0,0],[0,0],[0,0],[0,0],[0,0],[0,0],[0,0],[0,0],[0,0],[0,0],[0,0],[0,0],[0,0],[0,0],[0,0],[0,0],[0,0],[0,0],[0,0],[0,0],[0,0],[0,0],[0,0],[0,0],[0,0],[0,0],[0,0],[0,0],[0,0],[0,0],[0,0],[0,0],[0,0],[0,0],[0,0],[0,0],[0,0],[0,0],[0,0],[0,0],[0,0],[0,0],[0,0],[0,0],[0,0],[0,0],[0,0],[0,0],[0,0],[0,0],[0,0],[0,0],[0,0],[0,0],[0,0],[0,0],[0,0],[0,0],[0,0],[0,0],[0,0],[0,0],[0,0],[0,0],[0,0],[0,0],[0,0],[0,0],[0,0],[0,0],[0,0],[0,0],[0,0],[0,0],[0,0],[0,0],[0,0],[0,0],[0,0],[0,0],[0,-0.657],[0,0],[0,0],[0,0],[0,0],[0,0],[0,0],[0,0],[0,0],[0,0],[0,0],[0,0],[0,0],[0,0],[0,0],[0,0],[0,0],[0,0],[0,0]],"v":[[111.528,40.848],[140.633,68.738],[142.187,63.837],[118.56,30.111],[121.011,20.29],[133.481,34.414],[140.434,35.151],[149.578,29.055],[148.064,19.871],[132.943,7.719],[132.346,-3.317],[136.669,-9.134],[144.318,-6.684],[143.701,-1.464],[148.084,5.269],[151.968,2.5],[149.837,-5.468],[171.312,-13.138],[180.694,-21.007],[179.28,-35.211],[160.594,-54.813],[160.275,-70.75],[168.563,-70.75],[194.301,-51.128],[201.552,-53.08],[196.751,-59.415],[182.965,-67.782],[183.782,-80.232],[200.117,-80.212],[201.432,-95.651],[195.177,-103.839],[198.882,-107.823],[206.831,-99.855],[209.381,-103.221],[199.161,-114.875],[173.742,-117.943],[170.355,-124.676],[177.706,-135.095],[183.523,-130.812],[200.994,-129.278],[223.067,-144],[226.752,-139.398],[221.832,-131.728],[221.832,-124.059],[242.071,-107.504],[248.526,-110.871],[246.076,-121.907],[231.653,-135.394],[250.657,-136.629],[250.657,-142.147],[259.861,-143.98],[252.809,-148.841],[253.128,-152.586],[272.451,-149.458],[276.137,-152.586],[250.1,-163.622],[155.056,-168.523],[146.171,-173.025],[132.067,-175.117],[121.449,-175.475],[111.847,-165.754],[107.803,-166.072],[94.994,-175.575],[57.283,-175.575],[39.792,-185.993],[4.751,-183.782],[-21.824,-171.889],[-21.604,-158.084],[-29.832,-155.634],[-31.665,-169.439],[-34.713,-174.24],[-43.916,-176.491],[-46.048,-168.204],[-43.279,-161.471],[-76.009,-163.602],[-91.607,-156.351],[-93.978,-163.184],[-97.862,-162.168],[-100.711,-154.618],[-108.899,-148.223],[-128.84,-148.781],[-129.736,-153.183],[-108.899,-154.1],[-104.616,-157.785],[-129.776,-169.439],[-160.455,-168.523],[-177.607,-159.737],[-184.041,-148.243],[-195.376,-143.801],[-200.157,-138.601],[-199.062,-132.545],[-193.225,-131.728],[-189.679,-122.923],[-179.599,-126.987],[-177.925,-115.194],[-180.973,-115.194],[-189.28,-116.429],[-198.464,-114.895],[-207.349,-102.325],[-220.078,-100.333],[-221.911,-89.456],[-216.532,-88.181],[-218.066,-81.189],[-230.716,-83.719],[-242.31,-81.189],[-244.761,-74.734],[-242.749,-61.208],[-235.936,-58.02],[-224.541,-58.08],[-216.831,-58.777],[-214.461,-64.913],[-202.428,-80.571],[-194.52,-78.937],[-186.711,-85.989],[-185.256,-80.471],[-166.052,-67.523],[-168.403,-64.375],[-177.069,-64.833],[-173.742,-60.112],[-168.423,-58.937],[-162.188,-61.546],[-162.307,-69.057],[-159.538,-70.451],[-161.769,-72.822],[-174.579,-79.953],[-177.945,-89.456],[-167.287,-89.456],[-163.901,-86.089],[-154.717,-78.2],[-154.319,-68.658],[-144.816,-58.538],[-141.29,-72.403],[-134.697,-75.989],[-133.461,-64.654],[-127.027,-57.602],[-107.604,-57.921],[-101.886,-53.618],[-101.886,-43.498],[-108.939,-37.063],[-128.561,-37.063],[-140.533,-45.968],[-153.084,-44.733],[-153.084,-37.063],[-157.088,-37.063],[-161.371,-40.131],[-183.145,-45.649],[-183.145,-59.753],[-210.736,-57.602],[-219.302,-53],[-230.258,-53],[-235.637,-53.538],[-248.944,-46.147],[-248.944,-32.242],[-276.137,-12.62],[-273.885,-4.253],[-268.367,-4.253],[-269.802,3.715],[-273.686,5.13],[-273.885,25.987],[-250.398,52.761],[-240.159,52.761],[-239.541,51.128],[-221.154,51.128],[-215.855,46.227],[-205.417,46.227],[-199.699,51.944],[-184.181,53.578],[-186.232,74.236],[-168.961,104.676],[-178.065,122.047],[-177.447,130.234],[-170.276,137.366],[-170.276,157.008],[-160.893,169.658],[-160.893,185.993],[-133.083,185.993],[-112.226,164.538],[-105.691,152.885],[-97.325,151.032],[-97.325,141.231],[-91.806,134.677],[-80.172,118.74],[-82.623,94.436],[-87.723,85.412],[-64.793,63.499],[-39.513,27.362],[-44.414,25.111],[-70.65,30.629],[-77.403,27.262],[-104.994,-24.712],[-103.062,-26.963],[-75.71,6.245],[-74.993,16.564],[-68.658,22.899],[-55.789,22.063],[-28.895,2.6],[-20.449,-2.918],[-20.628,-9.652],[-29.593,-10.827],[-61.068,-26.306],[-60.869,-39.035],[-53.916,-39.035],[-52.881,-30.25],[-38.298,-21.863],[-21.624,-21.047],[14.533,-15.13],[23.019,-9.791],[23.019,-1.504],[21.923,9.751],[40.49,40.231],[46.466,41.605],[52.442,32.94],[55.749,8.257],[61.945,-5.03],[71.905,-8.755],[89.496,-7.082],[111.548,12.521],[111.548,40.848]],"c":true},"ix":2},"nm":"Path 4","mn":"ADBE Vector Shape - Group","hd":false},{"ty":"fl","c":{"a":0,"k":[0.364705890417,0.858823537827,0.482352942228,1],"ix":4},"o":{"a":0,"k":100,"ix":5},"r":1,"bm":0,"nm":"Fill 1","mn":"ADBE Vector Graphic - Fill","hd":false},{"ty":"tr","p":{"a":0,"k":[152.183,272.033],"ix":2},"a":{"a":0,"k":[0,0],"ix":1},"s":{"a":0,"k":[100,100],"ix":3},"r":{"a":0,"k":0,"ix":6},"o":{"a":0,"k":100,"ix":7},"sk":{"a":0,"k":0,"ix":4},"sa":{"a":0,"k":0,"ix":5},"nm":"Transform"}],"nm":"Group 4","np":5,"cix":2,"bm":0,"ix":4,"mn":"ADBE Vector Group","hd":false},{"ty":"gr","it":[{"ind":0,"ty":"sh","ix":1,"ks":{"a":0,"k":{"i":[[0,0],[0,0],[0,0],[0,0],[0,0],[0,0],[0,0]],"o":[[0,0],[0,0],[0,0],[0,0],[0,0],[0,0],[0,0]],"v":[[7.709,0.1],[8.128,-5.219],[3.407,-7.251],[-3.207,-5.737],[-8.128,2.132],[-8.128,7.251],[-2.41,7.251]],"c":true},"ix":2},"nm":"Path 1","mn":"ADBE Vector Shape - Group","hd":false},{"ty":"fl","c":{"a":0,"k":[0.364705890417,0.858823537827,0.482352942228,1],"ix":4},"o":{"a":0,"k":100,"ix":5},"r":1,"bm":0,"nm":"Fill 1","mn":"ADBE Vector Graphic - Fill","hd":false},{"ty":"tr","p":{"a":0,"k":[-83.294,157.457],"ix":2},"a":{"a":0,"k":[0,0],"ix":1},"s":{"a":0,"k":[100,100],"ix":3},"r":{"a":0,"k":0,"ix":6},"o":{"a":0,"k":100,"ix":7},"sk":{"a":0,"k":0,"ix":4},"sa":{"a":0,"k":0,"ix":5},"nm":"Transform"}],"nm":"Group 5","np":2,"cix":2,"bm":0,"ix":5,"mn":"ADBE Vector Group","hd":false},{"ty":"gr","it":[{"ind":0,"ty":"sh","ix":1,"ks":{"a":0,"k":{"i":[[0,0],[0,0],[0,0],[0,0],[0,0],[0,0],[0,0],[0,0],[0,0],[0,0],[0,0],[0,0],[0,0],[0,0],[0,0]],"o":[[0,0],[0,0],[0,0],[0,0],[0,0],[0,0],[0,0],[0,0],[0,0],[0,0],[0,0],[0,0],[0,0],[0,0],[0,0]],"v":[[-2.958,0.717],[-2.44,4.701],[-8.377,5.936],[-9.194,14.403],[-2.042,14.403],[7.46,13.487],[12.361,7.67],[7.142,5.618],[4.293,2.351],[0.01,-4.602],[-2.042,-14.403],[-10.11,-12.769],[-12.361,-9.323],[-12.361,-5.419],[-8.496,-2.749]],"c":true},"ix":2},"nm":"Path 1","mn":"ADBE Vector Shape - Group","hd":false},{"ty":"fl","c":{"a":0,"k":[0.364705890417,0.858823537827,0.482352942228,1],"ix":4},"o":{"a":0,"k":100,"ix":5},"r":1,"bm":0,"nm":"Fill 1","mn":"ADBE Vector Graphic - Fill","hd":false},{"ty":"tr","p":{"a":0,"k":[-65.774,153.572],"ix":2},"a":{"a":0,"k":[0,0],"ix":1},"s":{"a":0,"k":[100,100],"ix":3},"r":{"a":0,"k":0,"ix":6},"o":{"a":0,"k":100,"ix":7},"sk":{"a":0,"k":0,"ix":4},"sa":{"a":0,"k":0,"ix":5},"nm":"Transform"}],"nm":"Group 6","np":2,"cix":2,"bm":0,"ix":6,"mn":"ADBE Vector Group","hd":false},{"ty":"gr","it":[{"ind":0,"ty":"sh","ix":1,"ks":{"a":0,"k":{"i":[[0,0],[0,0],[0,0],[-0.518,0]],"o":[[0,0],[0,0],[0,0.398],[0.518,-0.02]],"v":[[2.301,3.715],[3.317,-2.719],[-3.317,-3.735],[-2.301,3.735]],"c":true},"ix":2},"nm":"Path 1","mn":"ADBE Vector Shape - Group","hd":false},{"ty":"fl","c":{"a":0,"k":[0.364705890417,0.858823537827,0.482352942228,1],"ix":4},"o":{"a":0,"k":100,"ix":5},"r":1,"bm":0,"nm":"Fill 1","mn":"ADBE Vector Graphic - Fill","hd":false},{"ty":"tr","p":{"a":0,"k":[-404.791,156.71],"ix":2},"a":{"a":0,"k":[0,0],"ix":1},"s":{"a":0,"k":[100,100],"ix":3},"r":{"a":0,"k":0,"ix":6},"o":{"a":0,"k":100,"ix":7},"sk":{"a":0,"k":0,"ix":4},"sa":{"a":0,"k":0,"ix":5},"nm":"Transform"}],"nm":"Group 7","np":2,"cix":2,"bm":0,"ix":7,"mn":"ADBE Vector Group","hd":false},{"ty":"gr","it":[{"ind":0,"ty":"sh","ix":1,"ks":{"a":0,"k":{"i":[[0,0],[0,0],[0,0],[0,0],[0,0],[0,0],[0,0],[0,0],[0,0],[0,0],[0,0]],"o":[[0,0],[0,0],[0,0],[0,0],[0,0],[0,0],[0,0],[0,0],[0,0],[0,0],[0,0]],"v":[[-1.793,2.171],[3.088,2.171],[3.088,-0.359],[6.554,0.02],[6.096,-4.323],[0.498,-3.466],[0.02,-0.657],[-6.235,0.02],[-6.554,0.02],[-6.554,4.323],[-1.793,4.323]],"c":true},"ix":2},"nm":"Path 1","mn":"ADBE Vector Shape - Group","hd":false},{"ty":"fl","c":{"a":0,"k":[0.364705890417,0.858823537827,0.482352942228,1],"ix":4},"o":{"a":0,"k":100,"ix":5},"r":1,"bm":0,"nm":"Fill 1","mn":"ADBE Vector Graphic - Fill","hd":false},{"ty":"tr","p":{"a":0,"k":[354.691,371.489],"ix":2},"a":{"a":0,"k":[0,0],"ix":1},"s":{"a":0,"k":[100,100],"ix":3},"r":{"a":0,"k":0,"ix":6},"o":{"a":0,"k":100,"ix":7},"sk":{"a":0,"k":0,"ix":4},"sa":{"a":0,"k":0,"ix":5},"nm":"Transform"}],"nm":"Group 8","np":2,"cix":2,"bm":0,"ix":8,"mn":"ADBE Vector Group","hd":false},{"ty":"gr","it":[{"ind":0,"ty":"sh","ix":1,"ks":{"a":0,"k":{"i":[[0,0],[0,0],[0,0],[0,0],[0,0],[0,0],[0,0],[0,0],[0,0],[0,0]],"o":[[0,0],[0,0],[0,0],[0,0],[0,0],[0,0],[0,0],[0,0],[0,0],[0,0]],"v":[[-0.378,1.345],[2.689,1.345],[2.689,-1.026],[4.901,-1.365],[4.901,-3.715],[0,-3.715],[-1.992,-1.365],[-4.901,1.345],[-4.901,3.715],[-0.378,3.257]],"c":true},"ix":2},"nm":"Path 1","mn":"ADBE Vector Shape - Group","hd":false},{"ty":"fl","c":{"a":0,"k":[0.364705890417,0.858823537827,0.482352942228,1],"ix":4},"o":{"a":0,"k":100,"ix":5},"r":1,"bm":0,"nm":"Fill 1","mn":"ADBE Vector Graphic - Fill","hd":false},{"ty":"tr","p":{"a":0,"k":[340.707,370.164],"ix":2},"a":{"a":0,"k":[0,0],"ix":1},"s":{"a":0,"k":[100,100],"ix":3},"r":{"a":0,"k":0,"ix":6},"o":{"a":0,"k":100,"ix":7},"sk":{"a":0,"k":0,"ix":4},"sa":{"a":0,"k":0,"ix":5},"nm":"Transform"}],"nm":"Group 9","np":2,"cix":2,"bm":0,"ix":9,"mn":"ADBE Vector Group","hd":false},{"ty":"gr","it":[{"ind":0,"ty":"sh","ix":1,"ks":{"a":0,"k":{"i":[[0,0],[0,0],[0,0],[0,0]],"o":[[0,0],[0,0],[0,0],[0,0]],"v":[[-2.46,-1.365],[2.46,-1.365],[2.46,1.365],[-2.46,1.365]],"c":true},"ix":2},"nm":"Path 1","mn":"ADBE Vector Shape - Group","hd":false},{"ty":"fl","c":{"a":0,"k":[0.364705890417,0.858823537827,0.482352942228,1],"ix":4},"o":{"a":0,"k":100,"ix":5},"r":1,"bm":0,"nm":"Fill 1","mn":"ADBE Vector Graphic - Fill","hd":false},{"ty":"tr","p":{"a":0,"k":[330.836,370.164],"ix":2},"a":{"a":0,"k":[0,0],"ix":1},"s":{"a":0,"k":[100,100],"ix":3},"r":{"a":0,"k":0,"ix":6},"o":{"a":0,"k":100,"ix":7},"sk":{"a":0,"k":0,"ix":4},"sa":{"a":0,"k":0,"ix":5},"nm":"Transform"}],"nm":"Group 10","np":2,"cix":2,"bm":0,"ix":10,"mn":"ADBE Vector Group","hd":false},{"ty":"gr","it":[{"ind":0,"ty":"sh","ix":1,"ks":{"a":0,"k":{"i":[[0,0],[0,0],[0,0],[0,0]],"o":[[0,0],[0,0],[0,0],[0,0]],"v":[[2.082,-1.614],[-2.082,-1.614],[-2.082,0.598],[1.145,1.614]],"c":true},"ix":2},"nm":"Path 1","mn":"ADBE Vector Shape - Group","hd":false},{"ty":"fl","c":{"a":0,"k":[0.364705890417,0.858823537827,0.482352942228,1],"ix":4},"o":{"a":0,"k":100,"ix":5},"r":1,"bm":0,"nm":"Fill 1","mn":"ADBE Vector Graphic - Fill","hd":false},{"ty":"tr","p":{"a":0,"k":[349.761,367.186],"ix":2},"a":{"a":0,"k":[0,0],"ix":1},"s":{"a":0,"k":[100,100],"ix":3},"r":{"a":0,"k":0,"ix":6},"o":{"a":0,"k":100,"ix":7},"sk":{"a":0,"k":0,"ix":4},"sa":{"a":0,"k":0,"ix":5},"nm":"Transform"}],"nm":"Group 11","np":2,"cix":2,"bm":0,"ix":11,"mn":"ADBE Vector Group","hd":false},{"ty":"gr","it":[{"ind":0,"ty":"sh","ix":1,"ks":{"a":0,"k":{"i":[[0,0],[0,0],[0,0],[0,0],[0,0],[0,0],[0,0],[0,0],[0,0],[0,0],[0,0],[0,0]],"o":[[0,0],[0,0],[0,0],[0,0],[0,0],[0,0],[0,0],[0,0],[0,0],[0,0],[0,0],[0,0]],"v":[[0.936,-13.785],[-11.753,-15.439],[-11.753,-5.618],[-7.251,-0.299],[-10.737,5],[-15.837,10.937],[-15.837,21.754],[-8.885,28.507],[-2.53,18.327],[9.921,0.1],[15.837,-28.507],[8.287,-28.507]],"c":true},"ix":2},"nm":"Path 1","mn":"ADBE Vector Shape - Group","hd":false},{"ty":"fl","c":{"a":0,"k":[0.364705890417,0.858823537827,0.482352942228,1],"ix":4},"o":{"a":0,"k":100,"ix":5},"r":1,"bm":0,"nm":"Fill 1","mn":"ADBE Vector Graphic - Fill","hd":false},{"ty":"tr","p":{"a":0,"k":[90.378,409.558],"ix":2},"a":{"a":0,"k":[0,0],"ix":1},"s":{"a":0,"k":[100,100],"ix":3},"r":{"a":0,"k":0,"ix":6},"o":{"a":0,"k":100,"ix":7},"sk":{"a":0,"k":0,"ix":4},"sa":{"a":0,"k":0,"ix":5},"nm":"Transform"}],"nm":"Group 12","np":2,"cix":2,"bm":0,"ix":12,"mn":"ADBE Vector Group","hd":false},{"ty":"gr","it":[{"ind":0,"ty":"sh","ix":1,"ks":{"a":0,"k":{"i":[[0,0],[0,0],[0,0],[0,0],[0,0]],"o":[[0,0],[0,0],[0,0],[0,0],[0,0]],"v":[[-6.454,0.329],[-3.885,7.261],[5.438,3.775],[6.454,-5.807],[-1.056,-7.261]],"c":true},"ix":2},"nm":"Path 1","mn":"ADBE Vector Shape - Group","hd":false},{"ty":"fl","c":{"a":0,"k":[0.364705890417,0.858823537827,0.482352942228,1],"ix":4},"o":{"a":0,"k":100,"ix":5},"r":1,"bm":0,"nm":"Fill 1","mn":"ADBE Vector Graphic - Fill","hd":false},{"ty":"tr","p":{"a":0,"k":[206.877,314.505],"ix":2},"a":{"a":0,"k":[0,0],"ix":1},"s":{"a":0,"k":[100,100],"ix":3},"r":{"a":0,"k":0,"ix":6},"o":{"a":0,"k":100,"ix":7},"sk":{"a":0,"k":0,"ix":4},"sa":{"a":0,"k":0,"ix":5},"nm":"Transform"}],"nm":"Group 13","np":2,"cix":2,"bm":0,"ix":13,"mn":"ADBE Vector Group","hd":false},{"ty":"gr","it":[{"ind":0,"ty":"sh","ix":1,"ks":{"a":0,"k":{"i":[[0,0],[0,0],[0,0],[0,0],[0,0],[0,0],[0,0],[0,0],[0,0],[0,0],[0,0],[0,0],[0,0],[0,0],[0,0],[0,0],[0,0],[0,0],[0,0],[0,0]],"o":[[0,0],[0,0],[0,0],[0,0],[0,0],[0,0],[0,0],[0,0],[0,0],[0,0],[0,0],[0,0],[0,0],[0,0],[0,0],[0,0],[0,0],[0,0],[0,0],[0,0]],"v":[[-9.024,-8.078],[-15.897,-7.879],[-15.379,-15.03],[-21.913,-18.895],[-31.216,-9.592],[-24.981,-1.942],[-11.514,-0.01],[-3.924,3.974],[-3.725,7.68],[-8.646,7.68],[-8.447,15.23],[7.909,14.194],[13.845,7.879],[20.18,7.241],[20.18,18.895],[31.216,18.895],[31.216,14.194],[25.718,14.194],[24.662,-0.01],[-1.673,-11.963]],"c":true},"ix":2},"nm":"Path 1","mn":"ADBE Vector Shape - Group","hd":false},{"ty":"fl","c":{"a":0,"k":[0.364705890417,0.858823537827,0.482352942228,1],"ix":4},"o":{"a":0,"k":100,"ix":5},"r":1,"bm":0,"nm":"Fill 1","mn":"ADBE Vector Graphic - Fill","hd":false},{"ty":"tr","p":{"a":0,"k":[405.689,356.837],"ix":2},"a":{"a":0,"k":[0,0],"ix":1},"s":{"a":0,"k":[100,100],"ix":3},"r":{"a":0,"k":0,"ix":6},"o":{"a":0,"k":100,"ix":7},"sk":{"a":0,"k":0,"ix":4},"sa":{"a":0,"k":0,"ix":5},"nm":"Transform"}],"nm":"Group 14","np":2,"cix":2,"bm":0,"ix":14,"mn":"ADBE Vector Group","hd":false},{"ty":"gr","it":[{"ind":0,"ty":"sh","ix":1,"ks":{"a":0,"k":{"i":[[0,0],[0,0],[0,0],[0,0],[0,0],[0,0],[0,0],[0,0],[0,0],[0,0],[0,0],[0,0],[0,0],[0,0],[0,0]],"o":[[0,0],[0,0],[0,0],[0,0],[0,0],[0,0],[0,0],[0,0],[0,0],[0,0],[0,0],[0,0],[0,0],[0,0],[0,0]],"v":[[28.019,-13.885],[23.577,-13.008],[23.437,-23.009],[15.309,-22.511],[14.273,-6.873],[7.122,-1.992],[-6.166,-0.139],[-27.402,15.001],[-31.047,17.949],[-31.047,23.009],[-19.891,21.296],[7.062,4.761],[14.692,-0.259],[22.84,-3.865],[31.047,-8.506]],"c":true},"ix":2},"nm":"Path 1","mn":"ADBE Vector Shape - Group","hd":false},{"ty":"fl","c":{"a":0,"k":[0.364705890417,0.858823537827,0.482352942228,1],"ix":4},"o":{"a":0,"k":100,"ix":5},"r":1,"bm":0,"nm":"Fill 1","mn":"ADBE Vector Graphic - Fill","hd":false},{"ty":"tr","p":{"a":0,"k":[452.195,474.262],"ix":2},"a":{"a":0,"k":[0,0],"ix":1},"s":{"a":0,"k":[100,100],"ix":3},"r":{"a":0,"k":0,"ix":6},"o":{"a":0,"k":100,"ix":7},"sk":{"a":0,"k":0,"ix":4},"sa":{"a":0,"k":0,"ix":5},"nm":"Transform"}],"nm":"Group 15","np":2,"cix":2,"bm":0,"ix":15,"mn":"ADBE Vector Group","hd":false},{"ty":"gr","it":[{"ind":0,"ty":"sh","ix":1,"ks":{"a":0,"k":{"i":[[0,0],[0,0],[0,0],[0,0],[0,0]],"o":[[0,0],[0,0],[0,0],[0,0],[0,0]],"v":[[-9.702,4.98],[0.956,6.116],[9.542,1.375],[9.702,-5.1],[0.319,-6.116]],"c":true},"ix":2},"nm":"Path 1","mn":"ADBE Vector Shape - Group","hd":false},{"ty":"fl","c":{"a":0,"k":[0.364705890417,0.858823537827,0.482352942228,1],"ix":4},"o":{"a":0,"k":100,"ix":5},"r":1,"bm":0,"nm":"Fill 1","mn":"ADBE Vector Graphic - Fill","hd":false},{"ty":"tr","p":{"a":0,"k":[387.541,484.86],"ix":2},"a":{"a":0,"k":[0,0],"ix":1},"s":{"a":0,"k":[100,100],"ix":3},"r":{"a":0,"k":0,"ix":6},"o":{"a":0,"k":100,"ix":7},"sk":{"a":0,"k":0,"ix":4},"sa":{"a":0,"k":0,"ix":5},"nm":"Transform"}],"nm":"Group 16","np":2,"cix":2,"bm":0,"ix":16,"mn":"ADBE Vector Group","hd":false},{"ty":"gr","it":[{"ind":0,"ty":"sh","ix":1,"ks":{"a":0,"k":{"i":[[0,0],[0,0],[0,0],[0,0],[0,0],[0,0],[0,0],[0,0],[0,0],[0,0],[0,0],[0,0],[0,0],[0,0],[0,0],[0,0],[0,0],[0,0],[0,0],[0,0],[0,0],[0,0],[0,0],[0,0],[0,0],[0,0],[0,0],[0,0],[0,0]],"o":[[0,0],[0,0],[0,0],[0,0],[0,0],[0,0],[0,0],[0,0],[0,0],[0,0],[0,0],[0,0],[0,0],[0,0],[0,0],[0,0],[0,0],[0,0],[0,0],[0,0],[0,0],[0,0],[0,0],[0,0],[0,0],[0,0],[0,0],[0,0],[0,0]],"v":[[64.684,-7.45],[53.667,-16.873],[52.851,-34.842],[45.579,-47.293],[39.045,-47.631],[36.396,-25.041],[23.885,-25.977],[20.399,-28.069],[19.981,-37.033],[26.595,-35.659],[32.153,-41.117],[20.3,-48.229],[6.335,-48.229],[-3.685,-34.025],[-7.769,-34.025],[-7.769,-38.527],[-19.742,-37.611],[-38.786,-15.957],[-48.847,-15.817],[-60.082,-8.068],[-60.919,25.439],[-67.652,31.973],[-67.652,37.91],[-34.922,26.674],[-8.427,25.619],[1.375,47.213],[31.495,48.229],[60.52,20.957],[67.652,4.642]],"c":true},"ix":2},"nm":"Path 1","mn":"ADBE Vector Shape - Group","hd":false},{"ty":"fl","c":{"a":0,"k":[0.364705890417,0.858823537827,0.482352942228,1],"ix":4},"o":{"a":0,"k":100,"ix":5},"r":1,"bm":0,"nm":"Fill 1","mn":"ADBE Vector Graphic - Fill","hd":false},{"ty":"tr","p":{"a":0,"k":[372.521,426.013],"ix":2},"a":{"a":0,"k":[0,0],"ix":1},"s":{"a":0,"k":[100,100],"ix":3},"r":{"a":0,"k":0,"ix":6},"o":{"a":0,"k":100,"ix":7},"sk":{"a":0,"k":0,"ix":4},"sa":{"a":0,"k":0,"ix":5},"nm":"Transform"}],"nm":"Group 17","np":2,"cix":2,"bm":0,"ix":17,"mn":"ADBE Vector Group","hd":false},{"ty":"gr","it":[{"ind":0,"ty":"sh","ix":1,"ks":{"a":0,"k":{"i":[[0,0],[0,0],[0,0],[0,0],[0,0],[0,0],[0,0],[0,0],[0,0],[0,0]],"o":[[0,0],[0,0],[0,0],[0,0],[0,0],[0,0],[0,0],[0,0],[0,0],[0,0]],"v":[[6.594,-10.777],[-4.223,-6.574],[-4.064,-4.144],[-6.753,-4.144],[-6.753,10.777],[-1.235,10.777],[-2.052,1.255],[2.251,2.809],[2.251,9.542],[6.753,9.144]],"c":true},"ix":2},"nm":"Path 1","mn":"ADBE Vector Shape - Group","hd":false},{"ty":"fl","c":{"a":0,"k":[0.364705890417,0.858823537827,0.482352942228,1],"ix":4},"o":{"a":0,"k":100,"ix":5},"r":1,"bm":0,"nm":"Fill 1","mn":"ADBE Vector Graphic - Fill","hd":false},{"ty":"tr","p":{"a":0,"k":[342.559,350.891],"ix":2},"a":{"a":0,"k":[0,0],"ix":1},"s":{"a":0,"k":[100,100],"ix":3},"r":{"a":0,"k":0,"ix":6},"o":{"a":0,"k":100,"ix":7},"sk":{"a":0,"k":0,"ix":4},"sa":{"a":0,"k":0,"ix":5},"nm":"Transform"}],"nm":"Group 18","np":2,"cix":2,"bm":0,"ix":18,"mn":"ADBE Vector Group","hd":false},{"ty":"gr","it":[{"ind":0,"ty":"sh","ix":1,"ks":{"a":0,"k":{"i":[[0,0],[0,0],[0,0],[0,0],[0,0],[0,0],[0,0],[0,0],[0,0],[0,0],[0,0],[0,0],[0,0],[0,0]],"o":[[0,0],[0,0],[0,0],[0,0],[0,0],[0,0],[0,0],[0,0],[0,0],[0,0],[0,0],[0,0],[0,0],[0,0]],"v":[[14.483,8.516],[17.013,6.843],[17.013,-13.337],[14.483,-14.393],[13.267,-20.688],[9.582,-20.688],[7.211,-14.313],[4.383,-11.783],[-17.013,-0.189],[-17.013,11.285],[-9.881,20.688],[8.148,20.688],[10.439,14.871],[14.483,11.186]],"c":true},"ix":2},"nm":"Path 1","mn":"ADBE Vector Shape - Group","hd":false},{"ty":"fl","c":{"a":0,"k":[0.364705890417,0.858823537827,0.482352942228,1],"ix":4},"o":{"a":0,"k":100,"ix":5},"r":1,"bm":0,"nm":"Fill 1","mn":"ADBE Vector Graphic - Fill","hd":false},{"ty":"tr","p":{"a":0,"k":[318.793,333.271],"ix":2},"a":{"a":0,"k":[0,0],"ix":1},"s":{"a":0,"k":[100,100],"ix":3},"r":{"a":0,"k":0,"ix":6},"o":{"a":0,"k":100,"ix":7},"sk":{"a":0,"k":0,"ix":4},"sa":{"a":0,"k":0,"ix":5},"nm":"Transform"}],"nm":"Group 19","np":2,"cix":2,"bm":0,"ix":19,"mn":"ADBE Vector Group","hd":false},{"ty":"gr","it":[{"ind":0,"ty":"sh","ix":1,"ks":{"a":0,"k":{"i":[[0,0],[0,0],[0,0],[0,0],[0,0],[0,0],[0,0],[0,0],[0,0],[0,0],[0,0],[0,0],[0,0],[0,0],[0,0],[0,0],[0,0]],"o":[[0,0],[0,0],[0,0],[0,0],[0,0],[0,0],[0,0],[0,0],[0,0],[0,0],[0,0],[0,0],[0,0],[0,0],[0,0],[0,0],[0,0]],"v":[[21.266,17.471],[6.126,17.889],[5.508,9.702],[7.958,10.737],[13.895,10.12],[13.277,2.57],[-3.058,2.769],[-7.56,-3.148],[-7.321,-6.255],[-28.398,-25.26],[-33.517,-21.156],[-3.476,15.638],[0.807,17.072],[0.807,19.104],[-4.911,19.104],[-3.476,23.626],[33.517,25.26]],"c":true},"ix":2},"nm":"Path 1","mn":"ADBE Vector Shape - Group","hd":false},{"ty":"fl","c":{"a":0,"k":[0.364705890417,0.858823537827,0.482352942228,1],"ix":4},"o":{"a":0,"k":100,"ix":5},"r":1,"bm":0,"nm":"Fill 1","mn":"ADBE Vector Graphic - Fill","hd":false},{"ty":"tr","p":{"a":0,"k":[288.324,343.54],"ix":2},"a":{"a":0,"k":[0,0],"ix":1},"s":{"a":0,"k":[100,100],"ix":3},"r":{"a":0,"k":0,"ix":6},"o":{"a":0,"k":100,"ix":7},"sk":{"a":0,"k":0,"ix":4},"sa":{"a":0,"k":0,"ix":5},"nm":"Transform"}],"nm":"Group 20","np":2,"cix":2,"bm":0,"ix":20,"mn":"ADBE Vector Group","hd":false},{"ty":"tr","p":{"a":0,"k":[288.324,343.54],"ix":2},"a":{"a":0,"k":[288.324,343.54],"ix":1},"s":{"a":0,"k":[100,100],"ix":3},"r":{"a":0,"k":0,"ix":6},"o":{"a":0,"k":100,"ix":7},"sk":{"a":0,"k":0,"ix":4},"sa":{"a":0,"k":0,"ix":5},"nm":"Transform"}],"nm":"Group 1","np":20,"cix":2,"bm":0,"ix":1,"mn":"ADBE Vector Group","hd":false},{"ty":"tr","p":{"a":0,"k":[288.324,343.54],"ix":2},"a":{"a":0,"k":[288.324,343.54],"ix":1},"s":{"a":0,"k":[100,100],"ix":3},"r":{"a":0,"k":0,"ix":6},"o":{"a":0,"k":100,"ix":7},"sk":{"a":0,"k":0,"ix":4},"sa":{"a":0,"k":0,"ix":5},"nm":"Transform"}],"nm":"Group 2","np":1,"cix":2,"bm":0,"ix":2,"mn":"ADBE Vector Group","hd":false}],"ip":0,"op":75,"st":0,"bm":0},{"ddd":0,"ind":7,"ty":4,"nm":"bg","sr":1,"ks":{"o":{"a":0,"k":100,"ix":11},"r":{"a":0,"k":0,"ix":10},"p":{"a":0,"k":[263.364,275,0],"ix":2},"a":{"a":0,"k":[0,0,0],"ix":1},"s":{"a":0,"k":[100,100,100],"ix":6}},"ao":0,"shapes":[{"ty":"gr","it":[{"ind":0,"ty":"sh","ix":1,"ks":{"a":0,"k":{"i":[[-99.612,0],[0,-99.612],[99.612,0],[0,99.612]],"o":[[99.612,0],[0,99.612],[-99.612,0],[0,-99.612]],"v":[[0,-180.364],[180.364,0],[0,180.364],[-180.364,0]],"c":true},"ix":2},"nm":"Path 1","mn":"ADBE Vector Shape - Group","hd":false},{"ty":"fl","c":{"a":0,"k":[0.701960802078,0.847058832645,0.956862747669,1],"ix":4},"o":{"a":0,"k":100,"ix":5},"r":1,"bm":0,"nm":"Fill 1","mn":"ADBE Vector Graphic - Fill","hd":false},{"ty":"tr","p":{"a":0,"k":[0,0],"ix":2},"a":{"a":0,"k":[0,0],"ix":1},"s":{"a":0,"k":[100,100],"ix":3},"r":{"a":0,"k":0,"ix":6},"o":{"a":0,"k":100,"ix":7},"sk":{"a":0,"k":0,"ix":4},"sa":{"a":0,"k":0,"ix":5},"nm":"Transform"}],"nm":"Group 1","np":2,"cix":2,"bm":0,"ix":1,"mn":"ADBE Vector Group","hd":false}],"ip":0,"op":75,"st":0,"bm":0}],"markers":[]}